<?xml version="1.0"?>
<opencv_storage>
<my_svm type_id="opencv-ml-svm">
  <svm_type>C_SVC</svm_type>
  <kernel><type>LINEAR</type></kernel>
  <C>1.</C>
  <term_criteria><epsilon>2.2204460492503131e-016</epsilon>
    <iterations>100</iterations></term_criteria>
  <var_all>4544</var_all>
  <var_count>4544</var_count>
  <class_count>2</class_count>
  <class_labels type_id="opencv-matrix">
    <rows>1</rows>
    <cols>2</cols>
    <dt>i</dt>
    <data>
      35 255</data></class_labels>
  <sv_total>1</sv_total>
  <support_vectors>
    <_>
      -6.20504636e-007 -8.64963681e-007 -1.11068471e-006
      -9.32843818e-007 -9.32843818e-007 -4.67506879e-007 3.17773947e-006
      3.65997312e-006 -6.57926364e-007 0. -1.95832126e-006
      -3.87449927e-006 -1.95832126e-006 -3.51740573e-006
      -1.90829860e-006 -1.04497735e-006 7.45612567e-007 2.08251436e-007
      0. -4.67506879e-007 0. 0. -6.57926364e-007 -1.09426048e-006
      -6.64545382e-007 -4.36334176e-007 -1.07951200e-006
      -6.43177827e-007 -6.43177827e-007 -6.43177827e-007
      -2.28211221e-007 -2.28211221e-007 -1.55908458e-006
      -1.55908458e-006 0. 0. 0. 0. -1.55908458e-006 -2.02659135e-006
      1.77043728e-006 9.05872071e-008 3.12373061e-007 3.12373061e-007
      3.12373061e-007 3.12373061e-007 3.12373061e-007 1.91370219e-007
      -1.18403614e-006 -7.16529257e-007 0. 0. 0. 0. 0. 0. 0. 0. 0. 0. 0.
      0. 0. 0. 0. 0. -7.17000205e-007 0. 0. 3.12373061e-007
      3.12373061e-007 1.17569436e-006 3.12373061e-007 0. 8.63321304e-007
      0. 0. -4.36334176e-007 -4.36334176e-007 1.51815300e-006 0. 0. 0.
      0. 0. 0. 0. 0. 8.63321304e-007 0. 0. 0. 2.00891279e-007
      3.12373061e-007 3.12373061e-007 3.12373061e-007 0. 0. 0.
      -2.21785839e-007 -2.21785839e-007 0. 0. 0. 2.44459045e-007 0. 0.
      -1.55908458e-006 -1.55908458e-006 0. 0. 0. 6.65286507e-007 0. 0.
      0. 0. 2.00891279e-007 1.06421260e-006 1.06421260e-006
      1.28920067e-006 0. 0. 1.11481768e-007 1.11481768e-007
      1.11481768e-007 1.11481768e-007 0. 0. 0. 0. 0. 0. 0. 0. 0. 0. 0.
      0. 0. 0. 0. 0. 0. 0. 0. 0. 0. 0. 0. 0. 0. 0. 0. 0. 0. 0. 0. 0. 0.
      0. 0. 0. 0. 0. 0. 0. 0. 0. 0. 0. 0. 0. 0. 0. 0. 0. 0. 0. 0. 0. 0.
      0. 0. 0. 0. 0. 0. 0. 0. 0. 0. 0. 0. 0. 0. 0. 0. 0. 0. 0. 0. 0. 0.
      0. 0. 0. 0. 0. 0. 0. 0. 0. 0. 0. 0. 0. 0. 0. 0. 0. 0. 0. 0. 0. 0.
      0. 0. 0. 0. 0. 0. 0. 0. 0. 0. 0. 0. 0. 0. 0. 0. 0. 0. 0. 0. 0. 0.
      0. 0. 0. 0. 0. 0. 0. 0. 2.91363631e-006 1.68912834e-006
      1.61210414e-006 1.43026693e-006 8.20631271e-007 -3.26149490e-007
      -9.08096496e-008 -2.00113027e-006 -1.14480054e-006 3.48122671e-006
      3.15152693e-006 -8.33949741e-007 -1.24198095e-006 3.79068865e-006
      4.94215146e-006 -5.78823403e-007 1.72691784e-007 -5.86157921e-006
      -3.26462509e-006 -7.19982836e-007 -3.39920484e-006
      -4.00139288e-006 -9.70129577e-007 2.13944782e-006 -4.54925839e-006
      1.44460591e-006 8.03070463e-007 -7.88293789e-007 4.74924150e-007
      -4.74488161e-006 -4.30635282e-007 -1.27297653e-006
      -5.49415574e-007 -1.21972761e-007 4.34151730e-007 -1.66460939e-006
      -2.70889950e-006 -6.38088466e-007 1.89733782e-006 1.46325885e-006
      -2.30986416e-006 -3.92260631e-007 -5.72113208e-007 2.43729687e-007
      4.68233793e-007 1.88211141e-006 9.91437787e-007 1.37325287e-006
      1.36729921e-006 3.89747265e-006 -2.94013667e-008 -1.17918205e-006
      -2.69683312e-007 -9.68327754e-007 -1.39964993e-006
      -1.69346004e-006 2.81146754e-006 -9.48760146e-008 9.76864953e-007
      3.71206340e-007 -4.88626938e-007 4.15876548e-006 2.66889674e-006
      1.60211357e-006 -8.39580025e-007 -1.42788792e-006 -3.65454952e-007
      1.65599249e-006 2.78747439e-006 3.63213326e-006 3.77243214e-006
      3.89016895e-006 -1.19910430e-006 -1.28439774e-006 3.46788767e-007
      -1.50695769e-006 2.27322380e-006 2.28920226e-006 1.66944588e-007
      1.28187958e-006 -5.00608576e-006 -3.69461395e-006 -4.53044004e-006
      -5.81045788e-006 -3.80571987e-006 1.54746101e-006 1.61439141e-006
      -2.07921812e-006 1.08925872e-006 -2.90168009e-006 -4.81332881e-006
      -6.11495125e-006 -2.98330883e-006 1.26758039e-006 2.76353876e-006
      4.97410883e-006 -1.21634901e-006 -2.05117226e-006 9.27459993e-008
      -1.64791072e-006 1.15429225e-006 1.65604445e-006 1.22834683e-006
      7.75764875e-007 3.17364288e-006 2.68536405e-006 2.64747655e-006
      4.09561699e-006 3.95831967e-006 2.88934729e-007 7.67285655e-007
      7.00010503e-007 5.34468882e-006 5.67104962e-006 1.02365698e-006 0.
      -5.72081717e-007 -1.04574852e-007 -3.60128581e-007
      -1.81463827e-006 2.02628166e-006 1.44748401e-006 1.79407982e-006
      2.31311878e-006 2.90827757e-007 -1.32985861e-006 -3.29133428e-007
      -2.24558590e-007 1.27420867e-006 -9.85180350e-007 5.61339164e-007
      2.88364708e-006 5.31239857e-006 6.81052052e-006 1.35780556e-006
      -2.94107986e-006 -1.59031947e-006 -1.80854613e-006
      -8.50036940e-007 -2.07569110e-006 -2.52828590e-006
      -4.30125340e-007 -1.20026027e-006 -3.78370856e-007 2.65305061e-006
      3.13458622e-006 1.75277171e-006 -1.91553198e-007 1.56814139e-007
      1.17626814e-006 1.28028739e-006 -1.26970099e-006 -3.15851509e-007
      -3.63910272e-006 -6.16480247e-006 -5.40060682e-006
      -1.12551413e-006 1.15147066e-006 -3.25403857e-006 -3.01050682e-006
      5.62257298e-007 1.54660029e-006 -1.17892500e-006 1.95573625e-006
      -2.48457781e-007 -3.46989759e-006 -4.77823050e-007 2.36459869e-006
      -7.69024666e-007 -6.00117801e-006 -9.21372020e-007
      -1.73590581e-006 4.94855158e-006 6.62809089e-006 4.25217013e-006
      -1.04680021e-006 2.09973700e-006 5.87328850e-006 7.70094346e-007
      4.38859786e-007 -2.51181632e-006 -1.22637539e-006 1.47528272e-006
      1.10723897e-006 -6.67144968e-006 -2.39493647e-006 4.69624820e-006
      4.92070239e-006 2.30400155e-006 -1.90196113e-006 -3.59366959e-006
      -1.70146666e-006 -9.97053803e-007 -2.29491184e-006
      -8.88819670e-007 7.05298248e-007 -1.02101421e-006 -2.62441267e-006
      -3.08791073e-006 -3.26581744e-006 2.84007228e-006 6.45324064e-007
      1.07120343e-006 2.56916383e-006 2.47955313e-007 -2.72934585e-006
      -3.23115478e-006 -2.28167005e-006 5.25139603e-006 4.68057169e-006
      3.89270826e-006 1.57612828e-006 2.27731402e-006 9.59121635e-008
      -2.96674398e-006 -5.61347633e-006 -3.91132517e-006
      -1.33066976e-006 1.46544210e-007 2.67289670e-006 4.37146537e-006
      1.78185803e-006 -1.47185733e-006 -2.81835446e-006 2.23378902e-006
      -1.17461902e-007 -5.24243603e-007 -4.87440673e-007
      -4.23549096e-007 -2.62240133e-006 1.75669379e-006 1.93388587e-006
      -5.31951457e-007 -5.67059396e-006 -4.87674379e-006 1.84831231e-006
      2.75984280e-006 2.68295798e-006 -1.59309627e-006 -2.45531453e-007
      2.04491371e-007 1.17667605e-006 1.76320464e-006 1.67546773e-007
      8.27771999e-007 5.08737401e-007 1.30728495e-006 -4.03430050e-007
      2.09988889e-006 2.09988889e-006 -8.62954664e-007 5.72493548e-007
      9.98372911e-007 1.32985861e-006 -3.28792908e-007 4.29953531e-007
      -5.23220951e-005 -5.23220951e-005 -5.23220951e-005
      -5.23220951e-005 -5.23220951e-005 -5.23220951e-005
      -5.23220951e-005 -5.23220951e-005 -5.23220951e-005
      -5.23220951e-005 -5.23220951e-005 -5.23220951e-005
      -5.23220951e-005 -5.23220951e-005 -5.23220951e-005
      -5.23220951e-005 -5.23220951e-005 -5.23220951e-005
      -5.23220951e-005 -5.23220951e-005 -5.23220951e-005
      -5.23220951e-005 -5.23220951e-005 -5.23220951e-005
      -5.23220951e-005 -5.23220951e-005 -5.23220951e-005
      -5.23220951e-005 -5.23220951e-005 -5.23220951e-005
      -5.23220951e-005 -5.23220951e-005 -5.23220951e-005
      -5.23220951e-005 -5.23220951e-005 -5.23220951e-005
      -5.23220951e-005 -5.23220951e-005 -5.23220951e-005
      -5.23220951e-005 -5.23220951e-005 -5.23220951e-005
      -5.23220951e-005 -5.23220951e-005 -5.23220951e-005
      -5.23220951e-005 -5.23220951e-005 -5.23220951e-005
      -5.23220951e-005 -5.23220951e-005 -5.23220951e-005
      -5.23220951e-005 -5.23220951e-005 -5.23220951e-005
      -5.23220951e-005 -5.23220951e-005 -4.52175882e-005
      -5.31857986e-005 -6.23272426e-005 -3.35445329e-005
      -5.74309452e-005 -6.59389552e-005 -4.20866090e-005
      -5.22330192e-005 -4.34033427e-005 -4.34033427e-005
      -4.34033427e-005 -4.34033427e-005 -4.34033427e-005
      -4.34033427e-005 -4.34033427e-005 -4.34033427e-005
      -4.34033427e-005 -4.34033427e-005 -4.34033427e-005
      -4.34033427e-005 -4.34033427e-005 -4.34033427e-005
      -4.34033427e-005 -4.34033427e-005 -4.34033427e-005
      -4.34033427e-005 -4.34033427e-005 -4.34033427e-005
      -4.34033427e-005 -4.34033427e-005 -4.34033427e-005
      -4.34033427e-005 -4.34033427e-005 -4.34033427e-005
      -4.34033427e-005 -4.34033427e-005 -4.34033427e-005
      -4.34033427e-005 -4.34033427e-005 -4.34033427e-005
      -4.34033427e-005 -4.34033427e-005 -4.34033427e-005
      -4.34033427e-005 -4.34033427e-005 -4.34033427e-005
      -4.34033427e-005 -4.34033427e-005 -4.34033427e-005
      -4.34033427e-005 -4.34033427e-005 -4.34033427e-005
      -4.34033427e-005 -4.34033427e-005 -4.34033427e-005
      -4.34033427e-005 -4.34033427e-005 -4.34033427e-005
      -4.34033427e-005 -4.34033427e-005 -4.34033427e-005
      -4.34033427e-005 -4.34033427e-005 -4.34033427e-005
      -4.67681421e-005 -4.80455892e-005 -5.18234046e-005
      -3.78395198e-005 -4.85947021e-005 1.49479856e-005 2.20577240e-005
      1.89532311e-005 1.75979803e-005 1.75979803e-005 1.75979803e-005
      1.75979803e-005 1.75979803e-005 1.75979803e-005 1.75979803e-005
      1.75979803e-005 1.75979803e-005 1.75979803e-005 1.75979803e-005
      1.75979803e-005 1.75979803e-005 1.75979803e-005 1.75979803e-005
      1.75979803e-005 1.75979803e-005 1.75979803e-005 1.75979803e-005
      1.75979803e-005 1.75979803e-005 1.75979803e-005 1.75979803e-005
      1.75979803e-005 1.75979803e-005 1.75979803e-005 1.75979803e-005
      1.75979803e-005 1.75979803e-005 1.75979803e-005 1.75979803e-005
      1.75979803e-005 1.75979803e-005 1.75979803e-005 1.75979803e-005
      1.75979803e-005 1.75979803e-005 1.75979803e-005 1.75979803e-005
      1.75979803e-005 1.75979803e-005 1.75979803e-005 1.75979803e-005
      1.75979803e-005 1.75979803e-005 1.75979803e-005 1.75979803e-005
      1.75979803e-005 1.75979803e-005 1.75979803e-005 1.75979803e-005
      1.75979803e-005 1.75979803e-005 1.75979803e-005 1.75979803e-005
      1.75979803e-005 1.75979803e-005 1.75979803e-005 1.75979803e-005
      1.75979803e-005 1.75979803e-005 1.75979803e-005 1.75979803e-005
      1.75979803e-005 1.75979803e-005 1.75979803e-005 1.75979803e-005
      1.75979803e-005 1.75979803e-005 1.75979803e-005 1.75979803e-005
      1.75979803e-005 1.75979803e-005 1.75979803e-005 1.75979803e-005
      1.75979803e-005 1.75979803e-005 1.75979803e-005 1.75979803e-005
      1.75979803e-005 1.75979803e-005 1.75979803e-005 1.75979803e-005
      1.75979803e-005 1.75979803e-005 1.75979803e-005 1.75979803e-005
      1.75979803e-005 1.75979803e-005 1.75979803e-005 1.75979803e-005
      1.75979803e-005 1.75979803e-005 1.75979803e-005 1.75979803e-005
      1.75979803e-005 1.75979803e-005 1.75979803e-005 1.75979803e-005
      1.75979803e-005 1.75979803e-005 1.75979803e-005 1.75979803e-005
      1.75979803e-005 1.75979803e-005 1.75979803e-005 1.75979803e-005
      1.75979803e-005 1.75979803e-005 1.75979803e-005 1.75979803e-005
      1.75979803e-005 1.91377294e-005 1.41109722e-005 1.31131656e-005
      1.82319800e-005 1.24977241e-005 2.22953568e-005 2.28791905e-005
      2.14503925e-005 2.20894817e-005 2.20894817e-005 2.20894817e-005
      2.20894817e-005 2.20894817e-005 2.20894817e-005 2.20894817e-005
      2.20894817e-005 2.20894817e-005 2.20894817e-005 2.20894817e-005
      2.20894817e-005 2.20894817e-005 2.20894817e-005 2.20894817e-005
      2.20894817e-005 2.20894817e-005 2.20894817e-005 2.20894817e-005
      2.20894817e-005 2.20894817e-005 2.20894817e-005 2.20894817e-005
      2.20894817e-005 2.20894817e-005 2.20894817e-005 2.20894817e-005
      2.20894817e-005 2.20894817e-005 2.20894817e-005 2.20894817e-005
      2.20894817e-005 2.20894817e-005 2.20894817e-005 2.20894817e-005
      2.20894817e-005 2.20894817e-005 2.20894817e-005 2.20894817e-005
      2.20894817e-005 2.20894817e-005 2.20894817e-005 2.20894817e-005
      2.20894817e-005 2.20894817e-005 2.20894817e-005 2.20894817e-005
      2.20894817e-005 2.20894817e-005 2.20894817e-005 2.20894817e-005
      2.20894817e-005 2.20894817e-005 2.20894817e-005 2.20894817e-005
      2.20894817e-005 7.28342729e-006 -2.98406230e-005 -3.60419144e-005
      -2.54146198e-005 -2.77256968e-005 -2.82264573e-005
      -2.56572093e-005 -3.15381185e-005 -2.82735054e-005
      -2.82735054e-005 -2.82735054e-005 -2.82735054e-005
      -2.82735054e-005 -2.82735054e-005 -2.82735054e-005
      -2.82735054e-005 -2.82735054e-005 -2.82735054e-005
      -2.82735054e-005 -2.82735054e-005 -2.82735054e-005
      -2.82735054e-005 -2.82735054e-005 -2.82735054e-005
      -2.82735054e-005 -2.82735054e-005 -2.82735054e-005
      -2.82735054e-005 -2.82735054e-005 -2.82735054e-005
      -2.82735054e-005 -2.82735054e-005 -2.82735054e-005
      -2.82735054e-005 -2.82735054e-005 -2.82735054e-005
      -2.82735054e-005 -2.82735054e-005 -2.82735054e-005
      -2.82735054e-005 -2.82735054e-005 -2.82735054e-005
      -2.82735054e-005 -2.82735054e-005 -2.82735054e-005
      -2.82735054e-005 -2.82735054e-005 -2.82735054e-005
      -2.82735054e-005 -2.82735054e-005 -2.82735054e-005
      -2.82735054e-005 -2.82735054e-005 -2.82735054e-005
      -2.82735054e-005 -2.82735054e-005 -3.28283750e-005
      -2.28412136e-005 -2.53409780e-005 -1.75590958e-005 1.73661078e-006
      -1.29702821e-005 -6.32508090e-006 -1.03803568e-005
      -1.23152349e-005 -1.23152349e-005 -1.23152349e-005
      -1.23152349e-005 -1.23152349e-005 -1.23152349e-005
      -1.23152349e-005 -1.23152349e-005 -1.23152349e-005
      -1.23152349e-005 -1.23152349e-005 -1.23152349e-005
      -1.23152349e-005 -1.23152349e-005 -1.23152349e-005
      -1.23152349e-005 -1.23152349e-005 -1.23152349e-005
      -1.23152349e-005 -1.23152349e-005 -1.23152349e-005
      -1.23152349e-005 -1.23152349e-005 -1.23152349e-005
      -1.23152349e-005 -1.23152349e-005 -1.23152349e-005
      -1.23152349e-005 -1.23152349e-005 -1.23152349e-005
      -1.23152349e-005 -1.23152349e-005 -1.23152349e-005
      -1.23152349e-005 -1.23152349e-005 -1.23152349e-005
      -1.23152349e-005 -1.23152349e-005 -1.23152349e-005
      -1.23152349e-005 -1.23152349e-005 -1.23152349e-005
      -1.23152349e-005 -1.23152349e-005 -1.23152349e-005
      -1.23152349e-005 -1.23152349e-005 -1.23152349e-005
      -1.45107360e-005 -1.76395697e-005 -1.13549904e-005
      -2.01333805e-005 -3.26535519e-005 -3.41845334e-005
      -2.81843422e-005 -3.38890859e-005 -3.21396510e-005
      -3.21396510e-005 -3.21396510e-005 -3.21396510e-005
      -3.21396510e-005 -3.21396510e-005 -3.21396510e-005
      -3.21396510e-005 -3.21396510e-005 -3.21396510e-005
      -3.21396510e-005 -3.21396510e-005 -3.21396510e-005
      -3.21396510e-005 -3.21396510e-005 -3.21396510e-005
      -3.21396510e-005 -3.21396510e-005 -3.21396510e-005
      -3.21396510e-005 -3.21396510e-005 -3.21396510e-005
      -3.21396510e-005 -3.21396510e-005 -3.21396510e-005
      -3.21396510e-005 -3.21396510e-005 -3.21396510e-005
      -3.21396510e-005 -3.21396510e-005 -3.21396510e-005
      -3.21396510e-005 -3.21396510e-005 -3.21396510e-005
      -3.21396510e-005 -3.21396510e-005 -3.21396510e-005
      -3.21396510e-005 -3.21396510e-005 -3.21396510e-005
      -3.21396510e-005 -3.21396510e-005 -3.21396510e-005
      -3.21396510e-005 -3.21396510e-005 -3.21396510e-005
      -3.21396510e-005 -3.21396510e-005 -4.37156414e-005
      -3.14519202e-005 -3.75560521e-005 -4.06293475e-005
      -2.85713049e-005 -3.33166972e-005 -4.24109239e-005
      -2.90700555e-005 -3.57159552e-005 -3.57159552e-005
      -3.57159552e-005 -3.57159552e-005 -3.57159552e-005
      -3.57159552e-005 -3.57159552e-005 -3.57159552e-005
      -3.57159552e-005 -3.57159552e-005 -3.57159552e-005
      -3.57159552e-005 -3.57159552e-005 -3.57159552e-005
      -3.57159552e-005 -3.57159552e-005 -3.57159552e-005
      -3.57159552e-005 -3.57159552e-005 -3.57159552e-005
      -3.57159552e-005 -3.57159552e-005 -3.57159552e-005
      -3.57159552e-005 -3.57159552e-005 -3.57159552e-005
      -3.57159552e-005 -3.57159552e-005 -3.57159552e-005
      -3.57159552e-005 -3.57159552e-005 -3.57159552e-005
      -3.57159552e-005 -3.57159552e-005 -3.57159552e-005
      -3.57159552e-005 -3.57159552e-005 -3.57159552e-005
      -3.57159552e-005 -3.57159552e-005 -3.57159552e-005
      -3.57159552e-005 -3.57159552e-005 -3.57159552e-005
      -3.57159552e-005 -3.57159552e-005 -3.57159552e-005
      -3.57159552e-005 -3.37367528e-005 -4.05566461e-005
      -3.83611950e-005 1.51055965e-005 1.51866216e-005 2.05979122e-005
      1.48165982e-005 1.61875250e-005 1.75979803e-005 1.75979803e-005
      1.75979803e-005 1.75979803e-005 1.75979803e-005 1.75979803e-005
      1.75979803e-005 1.75979803e-005 1.75979803e-005 1.75979803e-005
      1.75979803e-005 1.75979803e-005 1.75979803e-005 1.75979803e-005
      1.75979803e-005 1.75979803e-005 1.75979803e-005 1.75979803e-005
      1.75979803e-005 1.75979803e-005 1.75979803e-005 1.75979803e-005
      1.75979803e-005 1.75979803e-005 1.75979803e-005 1.71415595e-005
      1.78261926e-005 1.80544030e-005 1.75979803e-005 1.75979803e-005
      1.78261926e-005 1.71415595e-005 1.75979803e-005 1.75979803e-005
      1.78261926e-005 1.73697699e-005 1.73697699e-005 1.78261926e-005
      1.75979803e-005 1.75979803e-005 1.73697699e-005 1.73697699e-005
      1.80544030e-005 1.71415595e-005 1.78261926e-005 1.73697699e-005
      1.73697699e-005 1.80544030e-005 2.27291202e-005 8.22828224e-006
      3.95344978e-006 1.26424211e-005 1.10704286e-005 1.11100935e-005
      1.16389865e-005 1.03382245e-005 8.57603300e-006 8.57603300e-006
      8.57603300e-006 8.57603300e-006 8.57603300e-006 8.57603300e-006
      8.57603300e-006 8.57603300e-006 8.57603300e-006 8.57603300e-006
      8.57603300e-006 8.57603300e-006 8.57603300e-006 8.57603300e-006
      8.57603300e-006 8.57603300e-006 8.57603300e-006 8.57603300e-006
      8.57603300e-006 8.57603300e-006 8.57603300e-006 8.57603300e-006
      8.57603300e-006 8.57603300e-006 8.57603300e-006 8.80424432e-006
      8.34782168e-006 8.57603300e-006 8.57603300e-006 8.80424432e-006
      8.11961036e-006 8.57603300e-006 8.80424432e-006 8.80424432e-006
      8.34782168e-006 8.34782168e-006 8.34782168e-006 8.57603300e-006
      8.57603300e-006 8.80424432e-006 1.26602008e-005 7.76222259e-006
      1.03907187e-005 1.12080470e-005 6.05171408e-006 1.86573598e-005
      1.64729499e-005 2.27740838e-005 1.78261926e-005 1.75979803e-005
      1.75979803e-005 1.78261926e-005 1.78261926e-005 1.73697699e-005
      1.73697699e-005 1.75979803e-005 1.75979803e-005 1.75979803e-005
      1.75979803e-005 1.75979803e-005 1.75979803e-005 1.75979803e-005
      1.75979803e-005 1.75979803e-005 1.75979803e-005 1.75979803e-005
      1.75979803e-005 1.75979803e-005 1.75979803e-005 1.75979803e-005
      1.75979803e-005 1.75979803e-005 1.80544030e-005 1.73697699e-005
      1.73697699e-005 1.78261926e-005 1.71415595e-005 1.80544030e-005
      1.73697699e-005 1.73697699e-005 1.71415595e-005 1.78261926e-005
      1.75979803e-005 1.75979803e-005 1.80544030e-005 1.78261926e-005
      1.71415595e-005 1.75979803e-005 1.71415595e-005 1.78261926e-005
      1.75979803e-005 1.75979803e-005 1.80544030e-005 1.78261926e-005
      1.71415595e-005 1.75979803e-005 1.28027286e-005 2.43664945e-005
      6.12051226e-005 6.61905724e-005 6.87913634e-005 6.68314460e-005
      5.88374824e-005 6.61917875e-005 6.45769978e-005 6.45769978e-005
      6.45769978e-005 6.45769978e-005 6.45769978e-005 6.45769978e-005
      6.45769978e-005 6.45769978e-005 6.45769978e-005 6.45769978e-005
      6.45769978e-005 6.45769978e-005 6.45769978e-005 6.45769978e-005
      6.45769978e-005 6.45769978e-005 6.45769978e-005 6.45769978e-005
      6.45769978e-005 6.45769978e-005 6.45769978e-005 6.45769978e-005
      6.45769978e-005 6.45769978e-005 6.52607705e-005 6.41205697e-005
      6.48052082e-005 6.38932179e-005 6.38932179e-005 6.43487801e-005
      6.54889809e-005 6.52607705e-005 6.50325601e-005 6.48052082e-005
      6.45769978e-005 6.38932179e-005 6.38932179e-005 6.45769978e-005
      6.54889809e-005 6.50325601e-005 7.11225803e-005 5.00991264e-005
      6.74986804e-005 4.74502522e-005 8.28572374e-005 5.63459507e-005
      7.16513387e-005 5.00865754e-005 5.75274207e-005 5.75274207e-005
      5.75274207e-005 5.75274207e-005 5.75274207e-005 5.75274207e-005
      5.75274207e-005 5.75274207e-005 5.75274207e-005 5.75274207e-005
      5.75274207e-005 5.75274207e-005 5.75274207e-005 5.75274207e-005
      5.75274207e-005 5.75274207e-005 5.75274207e-005 5.75274207e-005
      5.75274207e-005 5.75274207e-005 5.75274207e-005 5.75274207e-005
      5.75274207e-005 5.75274207e-005 5.72992103e-005 5.75274207e-005
      5.72992103e-005 5.75274207e-005 5.75274207e-005 5.75274207e-005
      5.75274207e-005 5.72992103e-005 5.72992103e-005 5.79838452e-005
      5.70709999e-005 5.79838452e-005 5.72992103e-005 5.77556311e-005
      5.68427895e-005 5.77556311e-005 5.41596564e-005 5.27235788e-005
      5.21714537e-005 7.16235663e-005 5.18984125e-005 6.32631854e-005
      5.12530314e-005 1.10038862e-004 9.49222667e-005 9.49222667e-005
      9.49222667e-005 9.49222667e-005 9.49222667e-005 9.49222667e-005
      9.49222667e-005 9.49222667e-005 9.49222667e-005 9.49222667e-005
      9.49222667e-005 9.49222667e-005 9.49222667e-005 9.49222667e-005
      9.49222667e-005 9.49222667e-005 9.49222667e-005 9.49222667e-005
      9.49222667e-005 9.49222667e-005 9.49222667e-005 9.49222667e-005
      9.49222667e-005 9.49222667e-005 9.49222667e-005 9.49222667e-005
      9.49222667e-005 9.49222667e-005 9.49222667e-005 9.49222667e-005
      9.49222667e-005 9.49222667e-005 9.49222667e-005 9.49222667e-005
      9.49222667e-005 9.49222667e-005 9.49222667e-005 9.49222667e-005
      9.49222667e-005 9.49222667e-005 9.49222667e-005 9.49222667e-005
      9.49222667e-005 9.49222667e-005 9.49222667e-005 9.49222667e-005
      9.49222667e-005 9.49222667e-005 2.89260825e-005 2.89260825e-005
      2.89260825e-005 2.89260825e-005 2.89260825e-005 2.89260825e-005
      2.89260825e-005 2.89260825e-005 2.89260825e-005 2.89260825e-005
      2.89260825e-005 2.89260825e-005 2.89260825e-005 2.89260825e-005
      2.89260825e-005 2.89260825e-005 2.89260825e-005 2.89260825e-005
      2.89260825e-005 2.89260825e-005 2.89260825e-005 2.89260825e-005
      2.89260825e-005 2.89260825e-005 2.89260825e-005 2.89260825e-005
      2.89260825e-005 2.89260825e-005 2.89260825e-005 2.89260825e-005
      2.89260825e-005 2.89260825e-005 2.89260825e-005 2.89260825e-005
      2.89260825e-005 2.89260825e-005 2.89260825e-005 2.89260825e-005
      2.89260825e-005 2.89260825e-005 2.89260825e-005 2.89260825e-005
      2.89260825e-005 2.89260825e-005 2.89260825e-005 2.89260825e-005
      2.89260825e-005 2.89260825e-005 1.75979803e-005 1.75979803e-005
      1.75979803e-005 1.75979803e-005 1.75979803e-005 1.75979803e-005
      1.75979803e-005 1.75979803e-005 1.75979803e-005 1.75979803e-005
      1.75979803e-005 1.75979803e-005 1.75979803e-005 1.75979803e-005
      1.75979803e-005 1.75979803e-005 1.75979803e-005 1.75979803e-005
      1.75979803e-005 1.75979803e-005 1.75979803e-005 1.75979803e-005
      1.75979803e-005 1.75979803e-005 1.75979803e-005 1.75979803e-005
      1.75979803e-005 1.75979803e-005 1.75979803e-005 1.75979803e-005
      1.75979803e-005 1.75979803e-005 1.75979803e-005 1.75979803e-005
      1.75979803e-005 1.75979803e-005 1.75979803e-005 1.75979803e-005
      1.75979803e-005 1.75979803e-005 1.67321286e-005 1.95107514e-005
      1.92624520e-005 1.95376560e-005 1.89001676e-005 1.13424703e-005
      1.74639081e-005 2.09739155e-005 1.75979803e-005 1.75979803e-005
      1.75979803e-005 1.75979803e-005 1.75979803e-005 1.75979803e-005
      1.75979803e-005 1.75979803e-005 1.75979803e-005 1.75979803e-005
      1.75979803e-005 1.75979803e-005 1.75979803e-005 1.75979803e-005
      1.75979803e-005 1.75979803e-005 1.75979803e-005 1.75979803e-005
      1.75979803e-005 1.75979803e-005 1.75979803e-005 1.75979803e-005
      1.75979803e-005 1.75979803e-005 1.75979803e-005 1.71415595e-005
      1.78261926e-005 1.75979803e-005 1.75979803e-005 1.73697699e-005
      1.78261926e-005 1.75979803e-005 1.73697699e-005 1.78261926e-005
      1.75979803e-005 1.75979803e-005 1.75979803e-005 1.75979803e-005
      1.78261926e-005 1.73697699e-005 1.93060368e-005 1.66377249e-005
      1.87663591e-005 1.58540824e-005 2.24264368e-005 1.67410672e-005
      1.46900375e-005 1.85539029e-005 1.75979803e-005 1.75979803e-005
      1.75979803e-005 1.75979803e-005 1.75979803e-005 1.75979803e-005
      1.75979803e-005 1.75979803e-005 1.75979803e-005 1.75979803e-005
      1.75979803e-005 1.75979803e-005 1.75979803e-005 1.75979803e-005
      1.75979803e-005 1.75979803e-005 1.80544030e-005 1.73697699e-005
      1.73697699e-005 1.78261926e-005 1.71415595e-005 1.80544030e-005
      1.73697699e-005 1.73697699e-005 1.71415595e-005 1.78261926e-005
      1.75979803e-005 1.75979803e-005 1.80544030e-005 1.78261926e-005
      1.71415595e-005 1.75979803e-005 1.71415595e-005 1.78261926e-005
      1.75979803e-005 1.75979803e-005 1.80544030e-005 1.78261926e-005
      1.71415595e-005 1.75979803e-005 1.92743792e-005 1.81846754e-005
      1.70601943e-005 2.06494024e-005 1.66788323e-005 1.93393080e-005
      1.99770056e-005 1.67842627e-005 1.75979803e-005 1.75979803e-005
      1.75979803e-005 1.75979803e-005 1.75979803e-005 1.75979803e-005
      1.75979803e-005 1.75979803e-005 1.75979803e-005 1.75979803e-005
      1.75979803e-005 1.75979803e-005 1.75979803e-005 1.75979803e-005
      1.75979803e-005 1.75979803e-005 1.69142077e-005 1.82817548e-005
      1.75979803e-005 1.75979803e-005 1.75979803e-005 1.75979803e-005
      1.82817548e-005 1.69142077e-005 1.69142077e-005 1.82817548e-005
      1.75979803e-005 1.75979803e-005 1.75979803e-005 1.75979803e-005
      1.82817548e-005 1.69142077e-005 1.43364732e-005 2.43944887e-005
      1.91636718e-005 2.32869552e-005 1.67772268e-005 1.47851433e-005
      -5.16518267e-005 -4.81352617e-005 -5.15910506e-005
      -5.15910506e-005 -5.15910506e-005 -5.15910506e-005
      -5.15910506e-005 -5.15910506e-005 -5.15910506e-005
      -5.15910506e-005 -5.15910506e-005 -5.15910506e-005
      -5.15910506e-005 -5.15910506e-005 -5.15910506e-005
      -5.15910506e-005 -5.15910506e-005 -5.15910506e-005
      -5.15910506e-005 -5.29585996e-005 -5.09072779e-005
      -5.02235052e-005 -5.15910506e-005 -5.15910506e-005
      -5.09072779e-005 -5.29585996e-005 -5.15910506e-005
      -5.29585996e-005 -5.09072779e-005 -5.02235052e-005
      -5.15910506e-005 -5.15910506e-005 -5.09072779e-005
      -5.29585996e-005 -5.09072779e-005 -5.22748232e-005
      -5.09072779e-005 -5.15910506e-005 -5.22748232e-005
      -5.09072779e-005 -5.09072779e-005 -5.15910506e-005
      -5.45919320e-005 -6.83048202e-005 -7.35127251e-005
      -5.67708521e-005 -7.49586106e-005 -5.91877870e-005
      -6.33924283e-005 -7.09983869e-005 -6.82324462e-005
      -6.82324462e-005 -6.82324462e-005 -6.82324462e-005
      -6.82324462e-005 -6.82324462e-005 -6.82324462e-005
      -6.82324462e-005 -6.82324462e-005 -6.82324462e-005
      -6.82324462e-005 -6.82324462e-005 -6.82324462e-005
      -6.82324462e-005 -6.82324462e-005 -6.82324462e-005
      -6.82324462e-005 -6.80042358e-005 -6.80042358e-005
      -6.84606566e-005 -6.82324462e-005 -6.82324462e-005
      -6.84606566e-005 -6.80042358e-005 -6.80042358e-005
      -6.89170774e-005 -6.80042358e-005 -6.84606566e-005
      -6.77760254e-005 -6.86888670e-005 -6.77760254e-005
      -6.84606566e-005 -6.61825397e-005 -5.80399465e-005
      -8.28062402e-005 1.02956750e-004 7.37878945e-005 7.83639043e-005
      7.70715997e-005 6.84558981e-005 7.90080594e-005 7.90080594e-005
      7.90080594e-005 7.90080594e-005 7.90080594e-005 7.90080594e-005
      7.90080594e-005 7.90080594e-005 7.90080594e-005 7.90080594e-005
      7.90080594e-005 7.90080594e-005 7.90080594e-005 7.90080594e-005
      7.90080594e-005 7.90080594e-005 7.90080594e-005 7.90080594e-005
      7.90080594e-005 7.90080594e-005 7.90080594e-005 7.90080594e-005
      7.90080594e-005 7.90080594e-005 7.90080594e-005 7.90080594e-005
      7.90080594e-005 7.90080594e-005 7.90080594e-005 7.90080594e-005
      7.90080594e-005 7.90080594e-005 6.90894667e-005 8.86985435e-005
      8.67601848e-005 7.58285751e-005 -9.08623551e-005 -1.02471851e-004
      -1.04283929e-004 -8.41903238e-005 -9.88567917e-005
      -9.88567917e-005 -9.88567917e-005 -9.88567917e-005
      -9.88567917e-005 -9.88567917e-005 -9.88567917e-005
      -9.88567917e-005 -9.88567917e-005 -9.88567917e-005
      -9.88567917e-005 -9.88567917e-005 -9.88567917e-005
      -9.88567917e-005 -9.88567917e-005 -9.88567917e-005
      -9.88567917e-005 -9.88567917e-005 -9.88567917e-005
      -9.88567917e-005 -9.88567917e-005 -9.88567917e-005
      -9.88567917e-005 -9.88567917e-005 -9.88567917e-005
      -9.88567917e-005 -9.88567917e-005 -9.88567917e-005
      -9.88567917e-005 -9.88567917e-005 -9.88567917e-005
      -9.88567917e-005 -9.63284401e-005 -1.06480111e-004
      -9.88529791e-005 -9.86507657e-005 -7.30332104e-005
      -7.34385976e-005 -6.58511053e-005 -7.44465069e-005
      -6.81254751e-005 -6.81254751e-005 -6.81254751e-005
      -6.81254751e-005 -6.81254751e-005 -6.81254751e-005
      -6.81254751e-005 -6.81254751e-005 -6.81254751e-005
      -6.81254751e-005 -6.81254751e-005 -6.81254751e-005
      -6.81254751e-005 -6.81254751e-005 -6.81254751e-005
      -6.81254751e-005 -6.81254751e-005 -6.81254751e-005
      -6.81254751e-005 -6.81254751e-005 -6.81254751e-005
      -6.81254751e-005 -6.81254751e-005 -6.81254751e-005
      -6.81254751e-005 -6.81254751e-005 -6.81254751e-005
      -6.81254751e-005 -6.81254751e-005 -6.81254751e-005
      -6.81254751e-005 -6.81254751e-005 -7.25261561e-005
      -6.49972280e-005 -7.04334088e-005 1.74996239e-005 1.63812983e-005
      1.86109319e-005 1.43577827e-005 2.27117071e-005 1.75979803e-005
      1.75979803e-005 1.75979803e-005 1.75979803e-005 1.75979803e-005
      1.75979803e-005 1.75979803e-005 1.75979803e-005 1.75979803e-005
      1.71415595e-005 1.78261926e-005 1.80544030e-005 1.75979803e-005
      1.75979803e-005 1.78261926e-005 1.71415595e-005 1.75979803e-005
      1.75979803e-005 1.78261926e-005 1.73697699e-005 1.73697699e-005
      1.78261926e-005 1.75979803e-005 1.75979803e-005 1.73697699e-005
      1.73697699e-005 1.80544030e-005 1.71415595e-005 1.78261926e-005
      1.73697699e-005 1.73697699e-005 1.80544030e-005 2.18161422e-005
      1.46403772e-005 1.28745232e-005 1.77143011e-005 1.96369965e-005
      1.99829810e-005 1.79390790e-005 1.78025675e-005 1.75979803e-005
      1.75979803e-005 1.75979803e-005 1.75979803e-005 1.75979803e-005
      1.75979803e-005 1.75979803e-005 1.75979803e-005 1.75979803e-005
      1.78261926e-005 1.73697699e-005 1.75979803e-005 1.75979803e-005
      1.78261926e-005 1.71415595e-005 1.75979803e-005 1.78261926e-005
      1.78261926e-005 1.73697699e-005 1.73697699e-005 1.73697699e-005
      1.75979803e-005 1.75979803e-005 1.78261926e-005 1.88973700e-005
      1.35951232e-005 1.97667814e-005 1.95889934e-005 1.76580506e-005
      1.87394944e-005 1.93059168e-005 1.44913201e-005 1.74864999e-005
      1.74864999e-005 1.74864999e-005 1.74864999e-005 1.74864999e-005
      1.74864999e-005 1.74864999e-005 1.74864999e-005 1.74864999e-005
      1.74864999e-005 1.74864999e-005 1.74864999e-005 1.74864999e-005
      1.74864999e-005 1.74864999e-005 1.74864999e-005 1.74864999e-005
      1.74864999e-005 1.74864999e-005 1.74864999e-005 1.74864999e-005
      1.74864999e-005 1.74864999e-005 1.74864999e-005 1.74864999e-005
      1.74864999e-005 1.74864999e-005 1.74864999e-005 1.74864999e-005
      1.74864999e-005 1.74864999e-005 1.74864999e-005 3.98355542e-006
      4.27448467e-005 1.15095187e-004 1.35632115e-004 1.26666768e-004
      1.23676655e-004 1.13137088e-004 1.31552879e-004 1.23011851e-004
      1.23011851e-004 1.23011851e-004 1.23011851e-004 1.23011851e-004
      1.23011851e-004 1.23011851e-004 1.23011851e-004 1.23695616e-004
      1.22555430e-004 1.23240054e-004 1.22328071e-004 1.22328071e-004
      1.22783633e-004 1.23923834e-004 1.23695616e-004 1.23467413e-004
      1.23240054e-004 1.23011851e-004 1.22328071e-004 1.22328071e-004
      1.23011851e-004 1.23923834e-004 1.23467413e-004 1.31846027e-004
      1.12380010e-004 1.21921425e-004 1.35589944e-004 1.30583081e-004
      4.85161836e-005 4.49648214e-005 4.05394858e-005 4.50144798e-005
      4.50144798e-005 4.50144798e-005 4.50144798e-005 4.50144798e-005
      4.50144798e-005 4.50144798e-005 4.50144798e-005 4.47862694e-005
      4.50144798e-005 4.47862694e-005 4.50144798e-005 4.50144798e-005
      4.50144798e-005 4.50144798e-005 4.47862694e-005 4.47862694e-005
      4.54709007e-005 4.45580554e-005 4.54709007e-005 4.47862694e-005
      4.52426902e-005 4.43298450e-005 4.52426902e-005 4.44289508e-005
      4.50782791e-005 4.61972195e-005 4.50074804e-005 4.86324570e-005
      4.65186495e-005 4.29646352e-005 4.47485363e-005 4.49029976e-005
      4.49029976e-005 4.49029976e-005 4.49029976e-005 4.49029976e-005
      4.49029976e-005 4.49029976e-005 4.49029976e-005 4.49029976e-005
      4.49029976e-005 4.49029976e-005 4.49029976e-005 4.49029976e-005
      4.49029976e-005 4.49029976e-005 4.49029976e-005 4.49029976e-005
      4.49029976e-005 4.49029976e-005 4.49029976e-005 4.49029976e-005
      4.49029976e-005 4.49029976e-005 4.49029976e-005 4.49029976e-005
      4.49029976e-005 4.49029976e-005 4.49029976e-005 4.49029976e-005
      4.49029976e-005 4.49029976e-005 4.49029976e-005 4.49029976e-005
      4.49029976e-005 4.49029976e-005 4.49029976e-005 4.49029976e-005
      4.49029976e-005 4.49029976e-005 4.49029976e-005 4.49029976e-005
      4.49029976e-005 4.49029976e-005 4.49029976e-005 4.49029976e-005
      4.49029976e-005 4.49029976e-005 4.49029976e-005 4.49029976e-005
      4.49029976e-005 4.49029976e-005 4.49029976e-005 4.49029976e-005
      4.49029976e-005 4.49029976e-005 4.49029976e-005 4.49029976e-005
      4.49029976e-005 4.49029976e-005 4.49029976e-005 4.49029976e-005
      4.49029976e-005 4.49029976e-005 4.49029976e-005 1.75979803e-005
      1.75979803e-005 1.75979803e-005 1.75979803e-005 1.75979803e-005
      1.75979803e-005 1.75979803e-005 1.75979803e-005 1.75979803e-005
      1.75979803e-005 1.75979803e-005 1.75979803e-005 1.75979803e-005
      1.75979803e-005 1.75979803e-005 1.75979803e-005 1.75979803e-005
      1.75979803e-005 1.75979803e-005 1.75979803e-005 1.75979803e-005
      1.75979803e-005 1.75979803e-005 1.75979803e-005 1.68263232e-005
      1.97586942e-005 1.93566466e-005 1.95376560e-005 1.83696393e-005
      1.24035296e-005 1.70275744e-005 2.08797192e-005 1.75979803e-005
      1.75979803e-005 1.75979803e-005 1.75979803e-005 1.75979803e-005
      1.75979803e-005 1.75979803e-005 1.75979803e-005 1.75979803e-005
      1.71415595e-005 1.78261926e-005 1.75979803e-005 1.75979803e-005
      1.73697699e-005 1.78261926e-005 1.75979803e-005 1.73697699e-005
      1.78261926e-005 1.75979803e-005 1.75979803e-005 1.75979803e-005
      1.75979803e-005 1.78261926e-005 1.73697699e-005 2.04554926e-005
      1.32262367e-005 2.08424208e-005 1.66830723e-005 2.28661775e-005
      1.45628655e-005 1.87709320e-005 1.59886949e-005 1.80544030e-005
      1.73697699e-005 1.73697699e-005 1.78261926e-005 1.71415595e-005
      1.80544030e-005 1.73697699e-005 1.73697699e-005 1.71415595e-005
      1.78261926e-005 1.75979803e-005 1.75979803e-005 1.80544030e-005
      1.78261926e-005 1.71415595e-005 1.75979803e-005 1.71415595e-005
      1.78261926e-005 1.75979803e-005 1.75979803e-005 1.80544030e-005
      1.78261926e-005 1.71415595e-005 1.75979803e-005 1.73064363e-005
      2.13946460e-005 6.94093978e-005 7.26423386e-005 7.10603636e-005
      7.74381042e-005 6.60236765e-005 7.08045554e-005 7.35304347e-005
      7.53776767e-005 7.27625447e-005 7.46097867e-005 7.46097867e-005
      7.32189728e-005 7.46930455e-005 7.35304347e-005 7.18424708e-005
      7.53776767e-005 7.27625447e-005 7.62977579e-005 7.62977579e-005
      7.29907551e-005 7.32332846e-005 7.18424708e-005 7.17223229e-005
      6.64700638e-005 8.07241377e-005 6.35628312e-005 8.01023270e-005
      6.50575676e-005 1.92927928e-005 1.76457033e-005 1.86773341e-005
      1.63136883e-005 1.74306133e-005 1.99616279e-005 1.70583044e-005
      1.86773341e-005 1.79702893e-005 1.52343346e-005 1.81376581e-005
      1.56907572e-005 1.95893190e-005 1.92769930e-005 1.68300940e-005
      1.78261926e-005 1.77420789e-005 1.62304332e-005 1.80535426e-005
      1.61463195e-005 1.87381775e-005 1.87605892e-005 1.55233884e-005
      1.91328963e-005 1.69741907e-005 1.85940808e-005 1.91537456e-005
      5.72543177e-005 5.92701472e-005 6.35224133e-005 5.64010297e-005
      5.79301268e-005 6.34640164e-005 5.78501822e-005 5.94860612e-005
      5.94860612e-005 5.94860612e-005 5.94860612e-005 5.94860612e-005
      5.94860612e-005 5.94860612e-005 5.94860612e-005 5.94860612e-005
      5.94860612e-005 5.94860612e-005 5.94860612e-005 5.94860612e-005
      5.94860612e-005 5.94860612e-005 5.94860612e-005 5.87695322e-005
      6.09195922e-005 5.69532131e-005 6.11645955e-005 5.82380308e-005
      5.97134458e-005 5.86402530e-005 6.13525190e-005 5.94860612e-005
      5.94860612e-005 5.94860612e-005 5.94860612e-005 5.94860612e-005
      5.94860612e-005 5.94860612e-005 5.94860612e-005 5.94860612e-005
      5.94860612e-005 5.94860612e-005 5.94860612e-005 5.94860612e-005
      5.94860612e-005 5.94860612e-005 5.94860612e-005 5.95872298e-005
      6.06870817e-005 5.99223968e-005 6.03485059e-005 1.71684624e-005
      1.75945734e-005 1.68298884e-005 1.79297404e-005 1.75979803e-005
      1.75979803e-005 1.75979803e-005 1.75979803e-005 1.75979803e-005
      1.75979803e-005 1.75979803e-005 1.75979803e-005 1.75979803e-005
      1.75979803e-005 1.75979803e-005 1.75979803e-005 1.75979803e-005
      1.75979803e-005 1.75979803e-005 1.75979803e-005 1.80535608e-005
      1.21312396e-005 1.06683328e-005 1.24334974e-005 1.51325348e-005
      1.86822163e-005 1.34371221e-005 9.45172360e-006 1.22479705e-005
      1.22479705e-005 1.22479705e-005 1.22479705e-005 1.22479705e-005
      1.22479705e-005 1.22479705e-005 1.22479705e-005 1.22479705e-005
      1.22479705e-005 1.22479705e-005 1.22479705e-005 1.22479705e-005
      1.22479705e-005 1.22479705e-005 1.22479705e-005 1.53108194e-005
      1.77169186e-005 1.24504086e-005 1.56764854e-005 1.14034947e-005
      1.52114335e-005 1.76989452e-005 2.00473332e-005 1.75979803e-005
      1.75979803e-005 1.78261926e-005 1.73697699e-005 1.73697699e-005
      1.78261926e-005 1.75979803e-005 1.75979803e-005 1.73697699e-005
      1.73697699e-005 1.80544030e-005 1.71415595e-005 1.78261926e-005
      1.73697699e-005 1.73697699e-005 1.80544030e-005 1.98946855e-005
      -2.71316585e-005 -2.54286715e-005 -2.66759071e-005
      -3.27545349e-005 -2.95264326e-005 -2.53823091e-005
      -2.57936317e-005 -2.64655300e-005 -2.91438500e-005
      -3.15287798e-005 -3.20545769e-005 -2.98991981e-005
      -2.80568802e-005 -2.74175745e-005 -2.77547315e-005
      -2.56560561e-005 -2.78154275e-005 -2.92269651e-005
      -2.40521204e-005 -2.43877021e-005 -2.90053376e-005 2.62897720e-005
      1.70999028e-005 2.17594425e-005 2.17594425e-005 1.98432645e-005
      1.98432645e-005 1.98432645e-005 2.17594425e-005 2.36756205e-005
      2.36756205e-005 2.36756205e-005 2.36756205e-005 2.17594425e-005
      2.17594425e-005 2.17594425e-005 2.17594425e-005 2.17594425e-005
      2.17594425e-005 2.34178042e-005 1.87075748e-005 -2.03497821e-005
      -1.91784693e-005 -2.58028213e-005 -2.16237913e-005
      -3.45042499e-005 -2.64444043e-005 -2.72907273e-005
      -2.56018993e-005 -2.39139335e-005 -2.45977062e-005
      -2.65138842e-005 -2.77462896e-005 -2.49181267e-005
      -2.53745493e-005 -2.38834855e-005 -2.17424895e-005
      -2.72740599e-005 -2.09776026e-005 -2.71653898e-005 1.41326003e-004
      1.43176308e-004 1.43542726e-004 1.42890960e-004 1.42890960e-004
      1.42890960e-004 1.42890960e-004 1.42890960e-004 1.42890960e-004
      1.42890960e-004 1.42890960e-004 1.41775527e-004 1.43388970e-004
      1.40622127e-004 1.39304742e-004 1.36757662e-004 1.51850327e-004
      1.37511044e-004 -4.17931842e-005 -3.92219845e-005 -3.75813761e-005
      -4.12759473e-005 -3.73058065e-005 -3.93597693e-005 8.32756268e-005
      8.14972373e-005 -3.93597693e-005 -3.90841997e-005 -4.31921253e-005
      -3.93597693e-005 -4.12759473e-005 8.51918085e-005 8.53295933e-005
      8.51918085e-005 -4.14137321e-005 8.87696733e-005 8.87696733e-005
      8.87696733e-005 8.87696733e-005 8.87696733e-005 8.87696733e-005
      8.87696733e-005 8.87696733e-005 8.87696733e-005 8.87696733e-005
      8.87696733e-005 8.87696733e-005 8.87696733e-005 8.87696733e-005
      8.87696733e-005 8.87696733e-005 -1.07323394e-004 -1.07323394e-004
      -1.07323394e-004 -1.07323394e-004 -1.07323394e-004
      -1.07323394e-004 -1.07323394e-004 -1.07323394e-004
      -1.18117860e-004 -9.90522094e-005 -1.12973990e-004
      -1.01918973e-004 -1.20829784e-004 -9.98089236e-005
      -9.91104898e-005 -3.96250798e-005 -4.14652604e-005
      -4.30383152e-005 -4.46451377e-005 -4.41298471e-005
      -4.17859737e-005 -3.95170864e-005 -3.96032738e-005
      -3.97088079e-005 -4.54770015e-005 -4.04623752e-005
      -3.63372492e-005 -4.06030595e-005 -3.73411785e-005 1.60752170e-005
      1.36404251e-005 2.06198274e-005 2.13030198e-005 2.19876547e-005
      2.17594425e-005 2.17594425e-005 2.22158651e-005 2.19876547e-005
      2.13030198e-005 2.17594425e-005 2.30585320e-005 2.45029496e-005
      1.85527460e-005 2.08506135e-005 2.39729288e-005 2.17187862e-005
      2.10565377e-005 1.68828228e-005 1.78565297e-005 1.79854615e-005
      2.08502915e-005 1.72406144e-005 2.01378898e-005 1.64916746e-005
      -7.21338292e-005 -7.32665940e-005 -7.31945984e-005
      -1.02547187e-004 -1.02388760e-004 -1.02124031e-004
      -1.03454360e-004 -1.00313788e-004 -1.03441504e-004
      -1.01243597e-004 -9.88748870e-005 -3.66834975e-005
      -5.38651148e-005 -3.71791830e-005 -3.85565472e-005
      -4.47061029e-005 -5.04803247e-005 -4.12710433e-005
      -4.79424561e-005 -2.17335073e-005 -5.46363481e-005
      -3.42399835e-005 -1.95026951e-005 -2.25864314e-005
      -2.27072760e-005 -3.27860544e-005 -2.65351518e-005
      -2.86853556e-005 -2.67863816e-005 -2.71163990e-005
      -1.47260480e-005 -1.69732702e-005 -1.70591502e-005
      -1.72824002e-005 -1.85002318e-005 -1.35510827e-005
      -3.15702309e-005 -6.70058398e-006 -1.97475616e-004
      -1.76594316e-004 -1.94661596e-004 -1.84860677e-004
      -1.97412039e-004 -1.74676214e-004 -2.05911449e-004
      -6.05461755e-005 -7.09007509e-005 -6.39240243e-005
      -7.36976144e-005 -7.09006781e-005 -6.90977249e-005 2.01482126e-005
      1.87767546e-005 1.07346295e-005 2.19678805e-005 1.69892937e-005
      1.70940511e-005 1.55781308e-005 1.73387380e-005 1.61921325e-005
      -2.12767227e-005 -7.93846084e-006 -8.72694909e-006 5.08480480e-005
      4.99093658e-005 4.72832244e-006 8.22871880e-005 8.22871880e-005
      8.22871880e-005 8.22871880e-005 8.22871880e-005 8.22871880e-005
      8.22871880e-005 8.22871880e-005 8.22871880e-005 8.22871880e-005
      8.22871880e-005 8.22871880e-005 8.22871880e-005 8.22871880e-005
      8.22871880e-005 8.22871880e-005 8.22871880e-005 8.22871880e-005
      8.22871880e-005 8.22871880e-005 8.22871880e-005 8.22871880e-005
      8.22871880e-005 8.22871880e-005 8.22871880e-005 8.22871880e-005
      8.22871880e-005 8.22871880e-005 8.22871880e-005 8.22871880e-005
      8.22871880e-005 8.22871880e-005 8.22871880e-005 8.22871880e-005
      8.22871880e-005 8.22871880e-005 8.22871880e-005 8.22871880e-005
      8.22871880e-005 8.22871880e-005 8.22871880e-005 8.22871880e-005
      8.22871880e-005 8.22871880e-005 8.22871880e-005 8.22871880e-005
      8.22871880e-005 8.22871880e-005 8.22871880e-005 8.22871880e-005
      8.22871880e-005 8.22871880e-005 8.22871880e-005 8.22871880e-005
      8.22871880e-005 8.22871880e-005 6.85237173e-005 1.01437639e-004
      7.64853976e-005 8.39881322e-005 7.96483364e-005 6.77361531e-005
      8.59193678e-005 -5.40134934e-005 -5.77282190e-005 -5.77282190e-005
      -5.77282190e-005 -5.77282190e-005 -5.77282190e-005
      -5.77282190e-005 -5.77282190e-005 -5.77282190e-005
      -5.77282190e-005 -5.77282190e-005 -5.77282190e-005
      -5.77282190e-005 -5.77282190e-005 -5.77282190e-005
      -5.77282190e-005 -5.77282190e-005 -5.77282190e-005
      -5.77282190e-005 -5.77282190e-005 -5.77282190e-005
      -5.77282190e-005 -5.77282190e-005 -5.77282190e-005
      -5.77282190e-005 -5.77282190e-005 -5.77282190e-005
      -5.77282190e-005 -5.77282190e-005 -5.77282190e-005
      -5.77282190e-005 -5.77282190e-005 -5.77282190e-005
      -5.77282190e-005 -5.77282190e-005 -5.77282190e-005
      -5.77282190e-005 -5.77282190e-005 -5.77282190e-005
      -5.77282190e-005 -5.77282190e-005 -5.77282190e-005
      -5.77282190e-005 -5.77282190e-005 -5.77282190e-005
      -5.77282190e-005 -5.77282190e-005 -5.77282190e-005
      -5.77282190e-005 -5.77282190e-005 -5.77282190e-005
      -5.77282190e-005 -5.77282190e-005 -5.77282190e-005
      -5.77282190e-005 -5.77282190e-005 -5.77282190e-005
      -5.38368404e-005 -5.98595398e-005 -4.51986052e-005
      -7.09661181e-005 -5.80292617e-005 5.39327521e-005 3.14523131e-005
      3.00890952e-005 3.50662449e-005 3.50662449e-005 3.50662449e-005
      3.50662449e-005 3.50662449e-005 3.50662449e-005 3.50662449e-005
      3.50662449e-005 3.50662449e-005 3.50662449e-005 3.50662449e-005
      3.50662449e-005 3.50662449e-005 3.50662449e-005 3.50662449e-005
      3.50662449e-005 3.50662449e-005 3.50662449e-005 3.50662449e-005
      3.50662449e-005 3.50662449e-005 3.50662449e-005 3.50662449e-005
      3.50662449e-005 3.50662449e-005 3.50662449e-005 3.50662449e-005
      3.50662449e-005 3.50662449e-005 3.50662449e-005 3.50662449e-005
      3.50662449e-005 3.50662449e-005 3.50662449e-005 3.50662449e-005
      3.50662449e-005 3.50662449e-005 3.50662449e-005 3.50662449e-005
      3.50662449e-005 3.50662449e-005 3.50662449e-005 3.50662449e-005
      3.50662449e-005 3.50662449e-005 3.50662449e-005 3.50662449e-005
      3.50662449e-005 3.50662449e-005 3.50662449e-005 3.50662449e-005
      3.50662449e-005 3.50662449e-005 3.50662449e-005 3.50662449e-005
      3.50662449e-005 3.25102155e-005 4.00079225e-005 -1.83797638e-005
      -2.01794792e-005 -2.05028215e-007 -4.21784262e-006
      -1.76618032e-005 -1.17104491e-005 -9.83123391e-006
      -9.83123391e-006 -9.83123391e-006 -9.83123391e-006
      -9.83123391e-006 -9.83123391e-006 -9.83123391e-006
      -9.83123391e-006 -9.83123391e-006 -9.83123391e-006
      -9.83123391e-006 -9.83123391e-006 -9.83123391e-006
      -9.83123391e-006 -9.83123391e-006 -9.83123391e-006
      -9.83123391e-006 -9.83123391e-006 -9.83123391e-006
      -9.83123391e-006 -9.83123391e-006 -9.83123391e-006
      -9.83123391e-006 -9.83123391e-006 -9.83123391e-006
      -9.83123391e-006 -9.83123391e-006 -9.83123391e-006
      -9.83123391e-006 -9.83123391e-006 -9.83123391e-006
      -9.83123391e-006 -9.83123391e-006 -9.83123391e-006
      -9.83123391e-006 -9.83123391e-006 -9.83123391e-006
      -9.83123391e-006 -9.83123391e-006 -9.83123391e-006
      -9.83123391e-006 -9.83123391e-006 -9.83123391e-006
      -9.83123391e-006 -9.83123391e-006 -9.83123391e-006
      -9.83123391e-006 -9.83123391e-006 -6.34623393e-006
      -5.21941865e-006 -5.23820563e-006 -9.94441325e-006
      -1.13294909e-005 -1.69101913e-005 4.87796788e-005 4.60649972e-005
      4.49449399e-005 4.49449399e-005 4.49449399e-005 4.49449399e-005
      4.49449399e-005 4.49449399e-005 4.49449399e-005 4.49449399e-005
      4.49449399e-005 4.49449399e-005 4.49449399e-005 4.49449399e-005
      4.49449399e-005 4.49449399e-005 4.49449399e-005 4.49449399e-005
      4.49449399e-005 4.49449399e-005 4.49449399e-005 4.49449399e-005
      4.49449399e-005 4.49449399e-005 4.49449399e-005 4.49449399e-005
      4.49449399e-005 4.49449399e-005 4.49449399e-005 4.49449399e-005
      4.49449399e-005 4.49449399e-005 4.49449399e-005 4.49449399e-005
      4.49449399e-005 4.49449399e-005 4.49449399e-005 4.49449399e-005
      4.49449399e-005 4.49449399e-005 4.49449399e-005 4.49449399e-005
      4.49449399e-005 4.49449399e-005 4.49449399e-005 4.49449399e-005
      4.49449399e-005 4.49449399e-005 4.49449399e-005 4.49449399e-005
      4.49449399e-005 4.49449399e-005 4.49449399e-005 4.49449399e-005
      4.49449399e-005 4.49449399e-005 4.49449399e-005 4.49449399e-005
      4.62657845e-005 1.06204525e-005 -4.16594339e-005 -5.16189903e-006
      2.51831125e-006 -1.83044158e-005 -1.48818281e-005 -1.35947869e-006
      -8.98815051e-006 -8.98815051e-006 -8.98815051e-006
      -8.98815051e-006 -8.98815051e-006 -8.98815051e-006
      -8.98815051e-006 -8.98815051e-006 -9.20993625e-006
      -8.98815051e-006 -8.98815051e-006 -8.98815051e-006
      -8.98815051e-006 -8.98815051e-006 -8.88357499e-006
      -8.88357499e-006 -8.98815051e-006 -8.98815051e-006
      -8.98815051e-006 -8.98815051e-006 -8.98815051e-006
      -8.98815051e-006 -8.98815051e-006 -8.98815051e-006
      -8.98815051e-006 -8.98815051e-006 -8.98815051e-006
      -8.98815051e-006 -8.98815051e-006 -8.98815051e-006
      -8.98815051e-006 -8.98815051e-006 -8.98815051e-006
      -8.76636386e-006 -8.98815051e-006 -8.98815051e-006
      -8.98815051e-006 -8.98815051e-006 -9.09272512e-006
      -9.09272512e-006 -8.98815051e-006 -8.98815051e-006
      -8.98815051e-006 -8.76636386e-006 -8.76636386e-006
      -8.98815051e-006 -9.20993625e-006 -9.20993625e-006
      -2.11381630e-005 -2.11947008e-005 5.12873339e-006 3.44198415e-005
      3.88854060e-005 3.87248219e-005 3.18352431e-005 3.14351855e-005
      3.45981243e-005 3.45981243e-005 3.45981243e-005 3.45981243e-005
      3.45981243e-005 3.45981243e-005 3.45981243e-005 3.45981243e-005
      3.45981243e-005 3.45981243e-005 3.45981243e-005 3.45981243e-005
      3.45981243e-005 3.45981243e-005 3.45981243e-005 3.45981243e-005
      3.45981243e-005 3.45981243e-005 3.45981243e-005 3.45981243e-005
      3.45981243e-005 3.45981243e-005 3.45981243e-005 3.45981243e-005
      3.45981243e-005 3.45981243e-005 3.45981243e-005 3.45981243e-005
      3.45981243e-005 3.45981243e-005 3.45981243e-005 3.45981243e-005
      3.45981243e-005 3.45981243e-005 3.45981243e-005 3.45981243e-005
      3.45981243e-005 3.45981243e-005 3.45981243e-005 3.45981243e-005
      3.45981243e-005 3.45981243e-005 3.45981243e-005 3.45981243e-005
      3.45981243e-005 3.45981243e-005 3.45981243e-005 3.45981243e-005
      2.37855893e-005 4.05485189e-005 3.35779623e-005 2.80829499e-005
      4.95720815e-005 4.61999043e-005 3.87325381e-005 5.49934193e-005
      4.22399826e-005 4.22399826e-005 4.22399826e-005 4.22399826e-005
      4.22399826e-005 4.22399826e-005 4.22399826e-005 4.22399826e-005
      4.22399826e-005 4.22399826e-005 4.22399826e-005 4.22399826e-005
      4.22399826e-005 4.22399826e-005 4.22399826e-005 4.22399826e-005
      4.22399826e-005 4.22399826e-005 4.22399826e-005 4.22399826e-005
      4.22399826e-005 4.22399826e-005 4.22399826e-005 4.22399826e-005
      4.22399826e-005 4.22399826e-005 4.22399826e-005 4.22399826e-005
      4.22399826e-005 4.22399826e-005 4.22399826e-005 4.22399826e-005
      4.22399826e-005 4.22399826e-005 4.22399826e-005 4.22399826e-005
      4.22399826e-005 4.22399826e-005 4.22399826e-005 4.22399826e-005
      4.22399826e-005 4.22399826e-005 4.22399826e-005 4.22399826e-005
      4.22399826e-005 4.22399826e-005 4.22399826e-005 4.22399826e-005
      4.01719299e-005 4.96158318e-005 3.95828174e-005 3.42727399e-005
      -5.30531679e-006 -8.91234049e-006 -2.00093182e-005
      -1.24663284e-005 -9.60377747e-006 -9.60377747e-006
      -9.60377747e-006 -9.60377747e-006 -9.60377747e-006
      -9.60377747e-006 -9.60377747e-006 -9.60377747e-006
      -9.60377747e-006 -9.60377747e-006 -9.60377747e-006
      -9.60377747e-006 -9.60377747e-006 -9.60377747e-006
      -9.60377747e-006 -9.60377747e-006 -9.60377747e-006
      -9.60377747e-006 -9.60377747e-006 -9.60377747e-006
      -9.60377747e-006 -9.60377747e-006 -9.60377747e-006
      -9.60377747e-006 -9.60377747e-006 -9.60377747e-006
      -9.60377747e-006 -9.60377747e-006 -9.60377747e-006
      -9.60377747e-006 -9.60377747e-006 -9.60377747e-006
      -9.60377747e-006 -9.60377747e-006 -9.60377747e-006
      -9.60377747e-006 -9.60377747e-006 -9.60377747e-006
      -9.60377747e-006 -9.60377747e-006 -9.60377747e-006
      -9.60377747e-006 -9.60377747e-006 -9.60377747e-006
      -9.60377747e-006 -9.60377747e-006 -9.60377747e-006
      -9.60377747e-006 -6.28592034e-006 -1.37316983e-005
      -1.24136432e-005 -5.37492861e-006 -1.51109980e-005
      -1.03797065e-005 -6.62383854e-006 -1.09715957e-005
      -9.36437027e-006 -9.36437027e-006 -9.36437027e-006
      -9.36437027e-006 -9.36437027e-006 -9.36437027e-006
      -9.36437027e-006 -9.36437027e-006 -9.36437027e-006
      -9.36437027e-006 -9.36437027e-006 -9.36437027e-006
      -9.36437027e-006 -9.36437027e-006 -9.36437027e-006
      -9.36437027e-006 -9.36437027e-006 -9.36437027e-006
      -9.36437027e-006 -9.36437027e-006 -9.36437027e-006
      -9.36437027e-006 -9.36437027e-006 -9.36437027e-006
      -9.36437027e-006 -9.36437027e-006 -9.36437027e-006
      -9.36437027e-006 -9.36437027e-006 -9.36437027e-006
      -9.36437027e-006 -9.36437027e-006 -9.36437027e-006
      -9.36437027e-006 -9.36437027e-006 -9.36437027e-006
      -9.36437027e-006 -9.36437027e-006 -9.36437027e-006
      -9.36437027e-006 -9.36437027e-006 -9.36437027e-006
      -9.36437027e-006 -9.36437027e-006 -9.36437027e-006
      -9.36437027e-006 -9.36437027e-006 -9.36437027e-006
      -1.27728154e-005 -6.19627826e-005 -5.46641277e-005
      -5.05465687e-005 -6.56923221e-005 -5.27677330e-005
      -5.67057214e-005 -5.58348474e-005 -5.48452044e-005
      -5.48452044e-005 -5.48452044e-005 -5.48452044e-005
      -5.48452044e-005 -5.48452044e-005 -5.48452044e-005
      -5.48452044e-005 -5.47406307e-005 -5.47406307e-005
      -5.48452044e-005 -5.48452044e-005 -5.48452044e-005
      -5.48452044e-005 -5.48452044e-005 -5.50669902e-005
      -5.48452044e-005 -5.48452044e-005 -5.48452044e-005
      -5.48452044e-005 -5.48452044e-005 -5.48452044e-005
      -5.48452044e-005 -5.48452044e-005 -5.46234187e-005
      -5.48452044e-005 -5.48452044e-005 -5.48452044e-005
      -5.48452044e-005 -5.50669902e-005 -5.48452044e-005
      -5.46234187e-005 -5.48452044e-005 -5.48452044e-005
      -5.48452044e-005 -5.48452044e-005 -5.48452044e-005
      -5.48452044e-005 -5.48452044e-005 -5.48452044e-005
      -6.29518690e-005 -7.20129465e-005 -5.39060275e-005
      -5.53763166e-005 -6.02696236e-005 -6.25704415e-005 2.79110573e-005
      1.84071869e-005 1.82205622e-005 1.82205622e-005 1.82205622e-005
      1.82205622e-005 1.82205622e-005 1.82205622e-005 1.82205622e-005
      1.82205622e-005 1.82205622e-005 1.82205622e-005 1.82205622e-005
      1.82205622e-005 1.82205622e-005 1.82205622e-005 1.82205622e-005
      1.82205622e-005 1.82205622e-005 1.82205622e-005 1.82205622e-005
      1.82205622e-005 1.82205622e-005 1.82205622e-005 1.82205622e-005
      1.82205622e-005 1.82205622e-005 1.82205622e-005 1.82205622e-005
      1.82205622e-005 1.82205622e-005 1.82205622e-005 1.82205622e-005
      1.82205622e-005 1.82205622e-005 1.82205622e-005 1.82205622e-005
      1.82205622e-005 1.82205622e-005 1.82205622e-005 1.82205622e-005
      1.82205622e-005 1.82205622e-005 1.82205622e-005 1.82205622e-005
      1.82205622e-005 1.82205622e-005 1.82205622e-005 1.82205622e-005
      1.82205622e-005 2.13819931e-005 1.17944446e-005 -5.81060749e-006
      -3.19432220e-005 -2.88279662e-005 -1.60202853e-005
      -3.78643526e-005 -6.27090958e-006 -2.15312739e-005
      -2.15312739e-005 -2.15312739e-005 -2.15312739e-005
      -2.15312739e-005 -2.15312739e-005 -2.15312739e-005
      -2.15312739e-005 -2.15312739e-005 -2.15312739e-005
      -2.15312739e-005 -2.15312739e-005 -2.15312739e-005
      -2.15312739e-005 -2.15312739e-005 -2.15312739e-005
      -2.15312739e-005 -2.15312739e-005 -2.15312739e-005
      -2.15312739e-005 -2.15312739e-005 -2.15312739e-005
      -2.15312739e-005 -2.15312739e-005 -2.15312739e-005
      -2.15312739e-005 -2.15312739e-005 -2.15312739e-005
      -2.15312739e-005 -2.15312739e-005 -2.15312739e-005
      -2.15312739e-005 -2.15312739e-005 -2.15312739e-005
      -2.15312739e-005 -2.15312739e-005 -2.15312739e-005
      -2.15312739e-005 -2.15312739e-005 -2.15312739e-005
      -2.13738258e-005 -1.82057411e-005 -2.13973617e-005
      -2.04424668e-005 -1.76054964e-005 -7.87267127e-005
      -6.29780770e-005 -7.73490610e-005 -7.43236451e-005
      -7.43236451e-005 -7.43236451e-005 -7.43236451e-005
      -7.43236451e-005 -7.43236451e-005 -7.43236451e-005
      -7.43236451e-005 -7.43236451e-005 -7.43236451e-005
      -7.43236451e-005 -7.43236451e-005 -7.43236451e-005
      -7.43236451e-005 -7.43236451e-005 -7.43236451e-005
      -7.43236451e-005 -7.43236451e-005 -7.43236451e-005
      -7.43236451e-005 -7.43236451e-005 -7.43236451e-005
      -7.43236451e-005 -7.43236451e-005 -7.43236451e-005
      -7.43236451e-005 -7.43236451e-005 -7.43236451e-005
      -7.43236451e-005 -7.43236451e-005 -7.43236451e-005
      -7.43236451e-005 -7.43236451e-005 -7.43236451e-005
      -7.43236451e-005 -7.43236451e-005 -7.43236451e-005
      -7.43236451e-005 -7.43236451e-005 -7.43236451e-005
      -6.76715790e-005 -9.49803289e-005 -7.95887900e-005
      -7.31153341e-005 -6.54022369e-005 -8.22324873e-005
      -6.93838447e-005 7.67448873e-005 7.93695872e-005 7.93695872e-005
      7.93695872e-005 7.93695872e-005 7.93695872e-005 7.93695872e-005
      7.93695872e-005 7.93695872e-005 7.93695872e-005 7.93695872e-005
      7.93695872e-005 7.93695872e-005 7.93695872e-005 7.93695872e-005
      7.93695872e-005 7.93695872e-005 7.93695872e-005 7.93695872e-005
      7.93695872e-005 7.93695872e-005 7.93695872e-005 7.93695872e-005
      7.93695872e-005 7.93695872e-005 7.93695872e-005 7.93695872e-005
      7.93695872e-005 7.93695872e-005 7.93695872e-005 7.93695872e-005
      7.93695872e-005 7.93695872e-005 7.93695872e-005 7.93695872e-005
      7.93695872e-005 7.93695872e-005 7.93695872e-005 7.93695872e-005
      7.93695872e-005 7.93695872e-005 7.93695872e-005 7.93695872e-005
      7.93695872e-005 7.93695872e-005 7.93695872e-005 7.93695872e-005
      7.93695872e-005 7.93695872e-005 2.76574847e-005 2.76574847e-005
      2.76574847e-005 2.76574847e-005 2.76574847e-005 2.76574847e-005
      2.76574847e-005 2.76574847e-005 2.76574847e-005 2.78792704e-005
      2.74356989e-005 2.78792704e-005 2.74356989e-005 2.78792704e-005
      2.76574847e-005 2.78792704e-005 2.76574847e-005 2.76574847e-005
      2.76574847e-005 2.76574847e-005 2.76574847e-005 2.76574847e-005
      2.76574847e-005 2.76574847e-005 2.76574847e-005 2.76574847e-005
      2.76574847e-005 2.76574847e-005 2.76574847e-005 2.76574847e-005
      2.78792704e-005 2.76574847e-005 2.76574847e-005 2.76574847e-005
      2.76574847e-005 2.76574847e-005 2.76574847e-005 2.76574847e-005
      2.76574847e-005 2.76574847e-005 2.78792704e-005 2.76574847e-005
      2.76574847e-005 2.76574847e-005 2.76574847e-005 2.74356989e-005
      2.76574847e-005 2.78792704e-005 -9.36437027e-006 -9.36437027e-006
      -9.36437027e-006 -9.36437027e-006 -9.36437027e-006
      -9.36437027e-006 -9.36437027e-006 -9.36437027e-006
      -9.36437027e-006 -9.36437027e-006 -9.36437027e-006
      -9.36437027e-006 -9.36437027e-006 -9.36437027e-006
      -9.36437027e-006 -9.36437027e-006 -9.36437027e-006
      -9.36437027e-006 -9.36437027e-006 -9.36437027e-006
      -9.36437027e-006 -9.36437027e-006 -9.36437027e-006
      -9.36437027e-006 -9.36437027e-006 -9.36437027e-006
      -9.36437027e-006 -9.36437027e-006 -9.36437027e-006
      -9.36437027e-006 -9.36437027e-006 -9.36437027e-006
      -9.36437027e-006 -9.36437027e-006 -9.36437027e-006
      -9.36437027e-006 -9.36437027e-006 -9.36437027e-006
      -9.36437027e-006 -9.36437027e-006 -8.60576893e-006
      -2.71975068e-006 -9.70047495e-006 -1.54939571e-005
      -2.19543153e-006 -3.52491907e-006 -1.83623033e-005
      -5.16451619e-005 -5.49602737e-005 -5.49602737e-005
      -5.49602737e-005 -5.49602737e-005 -5.49602737e-005
      -5.49602737e-005 -5.49602737e-005 -5.49602737e-005
      -5.49602737e-005 -5.49602737e-005 -5.49602737e-005
      -5.49602737e-005 -5.49602737e-005 -5.49602737e-005
      -5.49602737e-005 -5.49602737e-005 -5.49602737e-005
      -5.49602737e-005 -5.49602737e-005 -5.49602737e-005
      -5.49602737e-005 -5.49602737e-005 -5.49602737e-005
      -5.49602737e-005 -5.49602737e-005 -5.49602737e-005
      -5.49602737e-005 -5.49602737e-005 -5.49602737e-005
      -5.49602737e-005 -5.49602737e-005 -5.49602737e-005
      -5.49602737e-005 -5.49602737e-005 -5.49602737e-005
      -5.49602737e-005 -5.49602737e-005 -5.49602737e-005
      -5.49602737e-005 -5.49602737e-005 -5.35397776e-005
      -5.46438750e-005 -5.47912277e-005 -6.39034188e-005
      -4.45575679e-005 3.72426075e-005 4.92655236e-005 3.92383590e-005
      4.53778666e-005 4.53778666e-005 4.53778666e-005 4.53778666e-005
      4.53778666e-005 4.53778666e-005 4.53778666e-005 4.53778666e-005
      4.53778666e-005 4.53778666e-005 4.53778666e-005 4.53778666e-005
      4.53778666e-005 4.53778666e-005 4.53778666e-005 4.53778666e-005
      4.53778666e-005 4.53778666e-005 4.53778666e-005 4.53778666e-005
      4.53778666e-005 4.53778666e-005 4.53778666e-005 4.53778666e-005
      4.53778666e-005 4.53778666e-005 4.53778666e-005 4.53778666e-005
      4.53778666e-005 4.53778666e-005 4.53778666e-005 4.53778666e-005
      4.53778666e-005 4.53778666e-005 4.53778666e-005 4.53778666e-005
      4.53778666e-005 4.53778666e-005 4.53778666e-005 4.53778666e-005
      5.28970704e-005 5.04370946e-005 -5.55580555e-005 -6.14309465e-005
      -5.52733763e-005 -5.66018171e-005 -5.43135757e-005
      -5.17084191e-005 -5.77282190e-005 -5.77282190e-005
      -5.77282190e-005 -5.77282190e-005 -5.77282190e-005
      -5.77282190e-005 -5.77282190e-005 -5.77282190e-005
      -5.77282190e-005 -5.77282190e-005 -5.77282190e-005
      -5.77282190e-005 -5.77282190e-005 -5.77282190e-005
      -5.77282190e-005 -5.77282190e-005 -5.77282190e-005
      -5.77282190e-005 -5.77282190e-005 -5.77282190e-005
      -5.77282190e-005 -5.77282190e-005 -5.77282190e-005
      -5.77282190e-005 -5.77282190e-005 -5.77282190e-005
      -5.77282190e-005 -5.77282190e-005 -5.77282190e-005
      -5.77282190e-005 -5.77282190e-005 -5.77282190e-005
      -4.73217660e-005 -5.96600876e-005 -5.51926423e-005
      -5.68858595e-005 -6.18834893e-005 -6.33122836e-005
      -4.42996452e-006 -5.85737916e-006 -9.60377747e-006
      -9.60377747e-006 -9.60377747e-006 -9.60377747e-006
      -9.60377747e-006 -9.60377747e-006 -9.60377747e-006
      -9.60377747e-006 -9.60377747e-006 -9.60377747e-006
      -9.60377747e-006 -9.60377747e-006 -9.60377747e-006
      -9.60377747e-006 -9.60377747e-006 -9.60377747e-006
      -9.60377747e-006 -9.60377747e-006 -9.60377747e-006
      -9.60377747e-006 -9.60377747e-006 -9.60377747e-006
      -9.60377747e-006 -9.60377747e-006 -9.60377747e-006
      -9.60377747e-006 -9.60377747e-006 -9.60377747e-006
      -9.60377747e-006 -9.60377747e-006 -9.60377747e-006
      -9.60377747e-006 -9.60377747e-006 -9.60377747e-006
      -9.60377747e-006 -9.60377747e-006 -9.60377747e-006
      -9.60377747e-006 -9.60377747e-006 -9.60377747e-006
      -7.05409320e-006 -1.23934096e-005 -6.08214395e-006
      -6.42333134e-006 -4.47832599e-006 -2.07539379e-005
      -1.67082471e-005 -5.48254229e-006 -1.01563737e-005
      -1.01563737e-005 -1.01563737e-005 -1.21146950e-005
      -1.21146950e-005 -1.21146950e-005 -1.21146950e-005
      -1.21146950e-005 -1.21146950e-005 -1.21146950e-005
      -1.21146950e-005 -1.21146950e-005 -1.21146950e-005
      -1.21146950e-005 -1.21146950e-005 -1.21146950e-005
      -1.21146950e-005 -1.21146950e-005 -1.21146950e-005
      -1.21146950e-005 -1.21146950e-005 -1.21146950e-005
      -1.21146950e-005 -1.21146950e-005 -1.21146950e-005
      -1.21146950e-005 -1.21146950e-005 -1.21146950e-005
      -1.21146950e-005 -1.21146950e-005 -1.21146950e-005
      -1.21146950e-005 -4.55195232e-006 -3.19229366e-005 1.23616946e-005
      -1.15170187e-004 -1.16807743e-004 -1.13175593e-004
      -1.04771847e-004 -1.20519318e-004 -1.12699352e-004
      -1.12699352e-004 -1.12699352e-004 -1.12699352e-004
      -1.12699352e-004 -1.12699352e-004 -1.12699352e-004
      -1.12699352e-004 -1.12699352e-004 -1.12699352e-004
      -1.12699352e-004 -1.12699352e-004 -1.12699352e-004
      -1.12699352e-004 -1.12699352e-004 -1.12699352e-004
      -1.12699352e-004 -1.12699352e-004 -1.12699352e-004
      -1.12699352e-004 -1.12699352e-004 -1.12699352e-004
      -1.12699352e-004 -1.12699352e-004 -1.12699352e-004
      -1.12699352e-004 -1.12699352e-004 -1.12699352e-004
      -1.12699352e-004 -1.12699352e-004 -1.12699352e-004
      -1.12699352e-004 -1.13940783e-004 -1.11711233e-004
      -1.19587203e-004 -1.05554049e-004 2.57486881e-005 3.82527141e-005
      3.14402314e-005 2.76587489e-005 3.49999063e-005 3.49999063e-005
      3.49999063e-005 3.49999063e-005 3.49999063e-005 3.49999063e-005
      3.49999063e-005 3.49999063e-005 3.49999063e-005 3.49999063e-005
      3.49999063e-005 3.49999063e-005 3.49999063e-005 3.49999063e-005
      3.49999063e-005 3.49999063e-005 3.49999063e-005 3.49999063e-005
      3.49999063e-005 3.49999063e-005 3.49999063e-005 3.49999063e-005
      3.49999063e-005 3.49999063e-005 3.49999063e-005 3.49999063e-005
      3.49999063e-005 3.49999063e-005 3.49999063e-005 3.49999063e-005
      3.49999063e-005 3.49999063e-005 3.10316136e-005 3.43505708e-005
      5.34356368e-005 2.04405133e-005 5.27469238e-005 2.77547788e-005
      4.26838160e-005 4.71544481e-005 4.13360685e-005 4.13360685e-005
      4.13360685e-005 4.13360685e-005 4.13360685e-005 4.13360685e-005
      4.13360685e-005 4.13360685e-005 4.13360685e-005 4.13360685e-005
      4.13360685e-005 4.13360685e-005 4.13360685e-005 4.13360685e-005
      4.13360685e-005 4.13360685e-005 4.13360685e-005 4.13360685e-005
      4.13360685e-005 4.13360685e-005 4.13360685e-005 4.13360685e-005
      4.13360685e-005 4.13360685e-005 4.13360685e-005 4.13360685e-005
      4.13360685e-005 4.13360685e-005 4.13360685e-005 4.13360685e-005
      4.13360685e-005 4.13360685e-005 4.59836447e-005 4.38663628e-005
      4.08573251e-005 -8.13925071e-005 -9.22400723e-005 -8.43632006e-005
      -8.67218187e-005 -9.02570537e-005 -8.54830578e-005
      -8.54830578e-005 -8.54830578e-005 -8.54830578e-005
      -8.54830578e-005 -8.54830578e-005 -8.54830578e-005
      -8.54830578e-005 -8.54830578e-005 -8.54830578e-005
      -8.54830578e-005 -8.54830578e-005 -8.54830578e-005
      -8.54830578e-005 -8.54830578e-005 -8.54830578e-005
      -8.54830578e-005 -8.54830578e-005 -8.54830578e-005
      -8.54830578e-005 -8.54830578e-005 -8.54830578e-005
      -8.54830578e-005 -8.54830578e-005 -8.54830578e-005
      -8.54830578e-005 -8.54830578e-005 -8.54830578e-005
      -8.54830578e-005 -8.54830578e-005 -8.54830578e-005
      -8.54830578e-005 -7.65990262e-005 -3.26599293e-005
      -3.08320778e-005 -2.97296410e-005 -1.38530868e-005
      -2.31006907e-005 -1.98466096e-005 -1.63276800e-005
      -2.19375033e-005 -2.19375033e-005 -2.19375033e-005
      -2.19375033e-005 -2.19375033e-005 -2.19375033e-005
      -2.19375033e-005 -2.19375033e-005 -2.19375033e-005
      -2.19375033e-005 -2.19375033e-005 -2.19375033e-005
      -2.19375033e-005 -2.19375033e-005 -2.19375033e-005
      -2.19375033e-005 -2.19375033e-005 -2.19375033e-005
      -2.19375033e-005 -2.19375033e-005 -2.19375033e-005
      -2.19375033e-005 -2.19375033e-005 -2.19375033e-005
      -2.60019369e-005 -1.92596544e-005 -1.64115627e-005
      -6.54777023e-006 -2.48767319e-005 -2.28707504e-005 2.92705754e-005
      1.73278349e-005 1.95466237e-005 1.95466237e-005 1.95466237e-005
      1.95466237e-005 1.95466237e-005 1.95466237e-005 1.95466237e-005
      1.95466237e-005 1.95466237e-005 1.95466237e-005 1.95466237e-005
      1.95466237e-005 1.95466237e-005 1.95466237e-005 1.95466237e-005
      1.95466237e-005 1.95466237e-005 1.95466237e-005 1.95466237e-005
      1.95466237e-005 1.95466237e-005 1.95466237e-005 1.95466237e-005
      1.95466237e-005 1.95466237e-005 1.95466237e-005 1.95466237e-005
      1.95466237e-005 1.95466237e-005 1.95466237e-005 1.95466237e-005
      1.95466237e-005 7.13626787e-006 3.53955547e-005 1.63192690e-005
      4.39103715e-005 2.28470017e-005 3.26486042e-005 3.52907846e-005
      4.10393368e-005 3.39877406e-005 3.39877406e-005 3.39877406e-005
      3.39877406e-005 3.39877406e-005 3.39877406e-005 3.39877406e-005
      3.39877406e-005 3.39877406e-005 3.39877406e-005 3.39877406e-005
      3.39877406e-005 3.39877406e-005 3.39877406e-005 3.39877406e-005
      3.39877406e-005 3.39877406e-005 3.39877406e-005 3.39877406e-005
      3.39877406e-005 3.39877406e-005 3.39877406e-005 3.39877406e-005
      3.39877406e-005 3.54256990e-005 3.45165354e-005 3.12212978e-005
      3.06336115e-005 3.97372460e-005 2.28100944e-005 3.28676542e-005
      3.21494263e-005 3.20179315e-005 3.20179315e-005 3.20179315e-005
      3.20179315e-005 3.20179315e-005 3.20179315e-005 3.20179315e-005
      3.20179315e-005 3.20179315e-005 3.20179315e-005 3.20179315e-005
      3.20179315e-005 3.20179315e-005 3.20179315e-005 3.20179315e-005
      3.20179315e-005 3.20179315e-005 3.20179315e-005 3.20179315e-005
      3.20179315e-005 3.20179315e-005 3.20179315e-005 3.20179315e-005
      3.20179315e-005 3.16110054e-005 4.16802577e-005 2.46940563e-005
      4.43568133e-005 4.16152579e-005 1.79113722e-005 3.60928898e-005
      -1.40014527e-005 -1.94046770e-005 -1.94046770e-005
      -1.94046770e-005 -1.94046770e-005 -1.94046770e-005
      -1.94046770e-005 -1.94046770e-005 -1.94046770e-005
      -1.94046770e-005 -1.94046770e-005 -1.94046770e-005
      -1.94046770e-005 -1.94046770e-005 -1.94046770e-005
      -1.94046770e-005 -1.94046770e-005 -1.94046770e-005
      -1.94046770e-005 -1.94046770e-005 -1.94046770e-005
      -1.94046770e-005 -1.94046770e-005 -1.94046770e-005
      -1.94046770e-005 -1.94046770e-005 -1.94046770e-005
      -1.94046770e-005 -1.94046770e-005 -1.94046770e-005
      -1.94046770e-005 -1.94046770e-005 -1.94046770e-005
      -9.60377747e-006 -9.60377747e-006 -9.60377747e-006
      -9.60377747e-006 -9.60377747e-006 -9.60377747e-006
      -9.60377747e-006 -9.60377747e-006 -9.60377747e-006
      -9.60377747e-006 -9.60377747e-006 -9.60377747e-006
      -9.60377747e-006 -9.60377747e-006 -9.38199173e-006
      -9.60377747e-006 -9.60377747e-006 -9.60377747e-006
      -9.60377747e-006 -9.60377747e-006 -9.60377747e-006
      -9.60377747e-006 -9.60377747e-006 -9.60377747e-006
      -9.38199173e-006 -9.60377747e-006 -9.60377747e-006
      -9.60377747e-006 -9.60377747e-006 -9.82556321e-006
      -9.60377747e-006 -9.38199173e-006 4.42797591e-006 4.42797591e-006
      4.42797591e-006 4.42797591e-006 4.42797591e-006 4.42797591e-006
      4.42797591e-006 4.42797591e-006 4.42797591e-006 4.42797591e-006
      4.42797591e-006 4.42797591e-006 4.42797591e-006 4.42797591e-006
      4.42797591e-006 4.42797591e-006 4.42797591e-006 4.42797591e-006
      4.42797591e-006 4.42797591e-006 4.42797591e-006 4.42797591e-006
      4.42797591e-006 4.42797591e-006 2.23650636e-006 1.40418906e-005
      1.09977473e-005 -2.38979510e-006 5.97626240e-006 1.17511936e-005
      2.71144529e-007 2.75197726e-006 4.12732516e-006 4.12732516e-006
      4.12732516e-006 4.12732516e-006 4.12732516e-006 4.12732516e-006
      4.12732516e-006 4.12732516e-006 4.12732516e-006 4.12732516e-006
      4.12732516e-006 4.12732516e-006 4.12732516e-006 4.12732516e-006
      4.12732516e-006 4.12732516e-006 4.12732516e-006 4.12732516e-006
      4.12732516e-006 4.12732516e-006 4.12732516e-006 4.12732516e-006
      4.12732516e-006 4.12732516e-006 -1.41074463e-006 -9.11601148e-007
      4.41533166e-006 7.06030914e-006 2.38995676e-006 3.44994514e-005
      3.21843509e-005 2.76203045e-005 3.23090280e-005 3.23090280e-005
      3.23090280e-005 3.23090280e-005 3.23090280e-005 3.23090280e-005
      3.23090280e-005 3.23090280e-005 3.20872423e-005 3.20872423e-005
      3.23090280e-005 3.25308138e-005 3.25308138e-005 3.23090280e-005
      3.23090280e-005 3.23090280e-005 3.23090280e-005 3.23090280e-005
      3.23090280e-005 3.23090280e-005 3.23090280e-005 3.23090280e-005
      3.25308138e-005 3.23090280e-005 3.33749376e-005 3.22129163e-005
      -1.32312352e-005 -1.54976315e-005 -7.90644935e-006
      -1.12313455e-005 -1.34432339e-005 -1.42176468e-005
      -9.60377747e-006 -9.60377747e-006 -9.60377747e-006
      -9.60377747e-006 -9.60377747e-006 -9.60377747e-006
      -9.60377747e-006 -9.60377747e-006 -9.60377747e-006
      -9.60377747e-006 -9.60377747e-006 -9.60377747e-006
      -9.60377747e-006 -9.60377747e-006 -9.60377747e-006
      -9.60377747e-006 -1.53397941e-005 -1.29411455e-005
      -1.21133271e-005 -1.25700890e-005 -2.25980011e-006
      -2.07903704e-005 -1.30319822e-004 -1.44827092e-004
      -1.37235809e-004 -1.37235809e-004 -1.37235809e-004
      -1.37235809e-004 -1.37235809e-004 -1.37235809e-004
      -1.37235809e-004 -1.37235809e-004 -1.37235809e-004
      -1.37235809e-004 -1.37235809e-004 -1.37235809e-004
      -1.37235809e-004 -1.37235809e-004 -1.37235809e-004
      -1.37235809e-004 -1.37235809e-004 -1.37235809e-004
      -1.37235809e-004 -1.37235809e-004 -1.37235809e-004
      -1.37235809e-004 -1.37235809e-004 -1.37235809e-004
      -1.35283030e-004 5.67102143e-005 7.35671929e-005 7.96029053e-005
      5.58092142e-005 7.64788638e-005 7.70128536e-005 6.97091964e-005
      7.23763296e-005 7.23763296e-005 7.23763296e-005 7.23763296e-005
      7.23763296e-005 7.23763296e-005 7.23763296e-005 7.23763296e-005
      7.23763296e-005 7.23763296e-005 7.23763296e-005 7.23763296e-005
      7.23763296e-005 7.23763296e-005 7.23763296e-005 7.23763296e-005
      7.88239486e-005 6.47981942e-005 7.51152184e-005 1.04261992e-004
      1.25329112e-004 1.13280657e-004 1.05495157e-004 1.22409663e-004
      1.13537011e-004 1.13537011e-004 1.13537011e-004 1.13537011e-004
      1.13537011e-004 1.13537011e-004 1.13537011e-004 1.13537011e-004
      1.13537011e-004 1.13537011e-004 1.13537011e-004 1.13537011e-004
      1.13537011e-004 1.13537011e-004 1.13537011e-004 1.13537011e-004
      1.19244956e-004 1.04391940e-004 1.08493507e-004 1.19997712e-004
      6.15896788e-005 7.24630299e-005 7.76490560e-005 5.98551233e-005
      7.23763296e-005 7.23763296e-005 7.23763296e-005 7.23763296e-005
      7.23763296e-005 7.23763296e-005 7.23763296e-005 7.23763296e-005
      7.23763296e-005 7.23763296e-005 7.23763296e-005 7.23763296e-005
      7.23763296e-005 7.23763296e-005 7.23763296e-005 7.23763296e-005
      7.21412871e-005 6.45360706e-005 7.34358109e-005 7.57270827e-005
      4.00959179e-005 4.27831947e-005 5.24478928e-005 4.26134793e-005
      4.22399826e-005 4.22399826e-005 4.22399826e-005 4.22399826e-005
      4.22399826e-005 4.22399826e-005 4.22399826e-005 4.22399826e-005
      4.22399826e-005 4.22399826e-005 4.22399826e-005 4.22399826e-005
      4.22399826e-005 4.22399826e-005 4.22399826e-005 4.22399826e-005
      3.70910639e-005 4.72750180e-005 4.69103907e-005 -1.69901141e-005
      -1.37894149e-005 -8.26859286e-006 -1.46296916e-005
      -6.93132006e-006 -9.60377747e-006 -9.60377747e-006
      -9.60377747e-006 -9.60377747e-006 -9.60377747e-006
      -9.60377747e-006 -9.60377747e-006 -9.60377747e-006
      -9.60377747e-006 -9.60377747e-006 -9.60377747e-006
      -9.60377747e-006 -9.60377747e-006 -9.60377747e-006
      -9.60377747e-006 -9.60377747e-006 -9.77614309e-006 4.49437248e-005
      4.34086796e-005 4.61832897e-005 4.43281097e-005 4.41706943e-005
      4.72969477e-005 4.21813238e-005 4.49449399e-005 4.49449399e-005
      4.49449399e-005 4.49449399e-005 4.49449399e-005 4.49449399e-005
      4.49449399e-005 4.49449399e-005 4.40144868e-005 4.13902744e-005
      2.89607251e-005 4.21067089e-005 3.66148815e-005 6.01587562e-005
      -1.61958578e-005 -5.93928371e-006 -1.29938244e-005
      -1.29938244e-005 -1.29938244e-005 -1.29938244e-005
      -1.29938244e-005 -1.29938244e-005 -1.29938244e-005
      -1.29938244e-005 -1.29938244e-005 -1.29938244e-005
      -1.29938244e-005 -1.29938244e-005 -1.29938244e-005
      -1.29938244e-005 -1.29938244e-005 -1.29938244e-005
      -6.62260300e-006 -2.15000964e-005 9.15261262e-005 8.29953424e-005
      8.00788330e-005 8.18109547e-005 8.11086138e-005 7.49774335e-005
      8.22871880e-005 8.22871880e-005 8.22871880e-005 8.22871880e-005
      8.22871880e-005 8.22871880e-005 8.22871880e-005 8.22871880e-005
      9.00904633e-005 7.40016039e-005 8.16265601e-005 7.80349292e-005
      7.82614661e-005 -6.62452658e-006 -1.14885879e-005 -1.48836016e-005
      -9.60377747e-006 -9.60377747e-006 -9.60377747e-006
      -9.60377747e-006 -9.60377747e-006 -9.60377747e-006
      -9.60377747e-006 -9.60377747e-006 -1.95934463e-005
      -6.97349742e-006 -1.79146900e-005 -1.80518527e-005
      -3.98551310e-006 -7.40465612e-006 -1.26200512e-005
      -1.79161561e-005 -1.35925511e-005 -1.35925511e-005
      -1.35925511e-005 -1.35925511e-005 -1.35925511e-005
      -1.35925511e-005 -1.35925511e-005 -1.35925511e-005
      -1.35925511e-005 -1.35925511e-005 -1.35925511e-005
      -1.35925511e-005 -1.35925511e-005 -1.35925511e-005
      -1.35925511e-005 -1.35925511e-005 -9.20199545e-006
      -9.20199545e-006 -9.20199545e-006 -9.20199545e-006
      -9.20199545e-006 -9.20199545e-006 -9.20199545e-006
      -9.20199545e-006 -9.20199545e-006 -9.20199545e-006
      -9.20199545e-006 -9.20199545e-006 -9.20199545e-006
      -9.20199545e-006 -9.20199545e-006 -9.20199545e-006
      -9.60377747e-006 -9.60377747e-006 -9.60377747e-006
      -9.60377747e-006 -9.60377747e-006 -9.60377747e-006
      -9.60377747e-006 -9.60377747e-006 -9.91691559e-006
      -2.33786668e-005 -1.92554726e-005 -3.50439950e-006
      -8.93521883e-006 -1.69150280e-005 -7.32838998e-006 1.34760840e-005
      1.13316655e-005 1.13316655e-005 1.13316655e-005 1.13316655e-005
      1.13316655e-005 1.13316655e-005 1.13316655e-005 1.13316655e-005
      1.43377983e-005 8.87144415e-006 1.13054411e-005 1.98028501e-005
      7.69612325e-006 -9.37537243e-006 -2.22456983e-005 1.27561941e-006
      -9.60377747e-006 -9.60377747e-006 -9.60377747e-006
      -9.60377747e-006 -9.60377747e-006 -9.60377747e-006
      -9.60377747e-006 -9.60377747e-006 -1.88411377e-005
      -1.26812147e-005 2.28795739e-006 2.92720488e-005 2.06133827e-005
      2.76200135e-005 2.72279922e-005 1.38500636e-005 1.10469646e-005
      3.85330241e-005 1.42332228e-005 2.11311999e-005 3.16621226e-005
      1.64050343e-005 1.90326307e-006 1.08439081e-005 4.12732516e-006
      4.12732516e-006 4.12732516e-006 4.12732516e-006 4.12732516e-006
      4.12732516e-006 4.12732516e-006 4.12732516e-006 8.84133260e-006
      -7.59281829e-005 -4.91442079e-005 -5.87569921e-005
      -7.50489562e-005 -5.28322562e-005 -4.71225176e-005
      -6.43460517e-005 -5.97538856e-005 -5.88087569e-005
      -5.92642828e-005 -9.48456545e-006 -7.44233921e-006
      -8.64543017e-006 -1.30414292e-005 -1.72614400e-005
      -1.24663284e-005 -1.80509960e-005 -1.08706618e-005
      -3.34699575e-006 3.23144195e-005 4.15411414e-005 4.76575078e-005
      4.01719299e-005 4.16371804e-005 4.52531094e-005 4.11368819e-005
      3.48459726e-005 3.81287759e-006 1.33337187e-006 -2.01775924e-006
      -2.34425534e-006 4.51665528e-006 -1.06696234e-006 8.00709040e-006
      -7.72346266e-006 -1.21925241e-005 -7.04757713e-006
      -8.44601982e-006 -9.26526627e-006 -1.35218479e-005
      -1.32886271e-004 -1.48908934e-004 -1.43482699e-004
      -1.42883975e-004 -1.48234831e-004 -1.74785146e-005
      -5.17652916e-006 -2.68540475e-007 -2.27444907e-005
      -6.30482173e-005 -7.29647509e-005 -6.41982406e-005 3.54368831e-006
      -1.00810157e-005 -8.82387212e-006</_></support_vectors>
  <decision_functions>
    <_>
      <sv_count>1</sv_count>
      <rho>1.5579925968436243e+000</rho>
      <alpha>
        1.</alpha>
      <index>
        0</index></_></decision_functions></my_svm>
</opencv_storage>
